Workbook

Sheet Geral
H2: Extrato BB 2025 Geral
C4: Janeiro | D4: Fevereiro | E4: Março | F4: Abril | G4: Maio | H4: Junho | I4: Agosto | J4: Setembro | K4: Outubro | L4: Novembro | M4: Dezembro
B5: SESAP | C5: =Jan!J1 -> 540014.34 | D5: =Fev!J1 -> 547072.6 | E5: =Mar!I1 -> 354538.76 | F5: =Abr!M1 -> 786969.58 | G5: =Mai!M1 -> 828438.8 | H5: =Jun!M1 -> 954127.35 | I5: 0 | J5: 0 | K5: 0 | L5: 0 | M5: 0
L8: Geral | M8: =SUM(C5:M5) -> 4011161.4
H12: Extrato BB 2025 Hematologia
C14: Janeiro | D14: Fevereiro | E14: Março | F14: Abril | G14: Maio | H14: Junho | I14: Agosto | J14: Setembro | K14: Outubro | L14: Novembro | M14: Dezembro
C15: =Jan!J11 -> 0 | D15: =Fev!J11 -> 0 | E15: =Mar!I10 -> 0 | F15: =Abr!K1 -> 88043.08 | G15: =Mai!K1 -> 162800.05 | H15: 0 | I15: 0 | J15: 0 | K15: 0 | L15: 0 | M15: 0
L18: Geral | M18: =SUM(C15:M15) -> 250843.13
H22: Extrato BB 2025 Coagulação
C24: Janeiro | D24: Fevereiro | E24: Março | F24: Abril | G24: Maio | H24: Junho | I24: Agosto | J24: Setembro | K24: Outubro | L24: Novembro | M24: Dezembro
C25: =Jan!J21 -> 0 | D25: =Fev!J21 -> 0 | F25: =Abr!K60 -> 10125.28 | G25: =Mai!K8 -> 22726.57 | H25: =Jun!K7 -> 3753.14 | I25: 0 | J25: 0 | K25: 0 | L25: 0 | M25: 0
L28: Geral | M28: =SUM(C25:M25) -> 36604.99
H33: Extrato BB 2025 TT/TTPA
C35: Janeiro | D35: Fevereiro | E35: Março | F35: Abril | G35: Maio | H35: Junho | I35: Agosto | J35: Setembro | K35: Outubro | L35: Novembro | M35: Dezembro
C36: =Jan!J32 -> 0 | D36: =Fev!J32 -> 0 | E36: =Mar!I31 -> 0 | F36: =Abr!K62 -> 4462.09 | G36: 0 | H36: 0 | I36: 0 | J36: 0 | K36: 0 | L36: 0 | M36: 0
L39: Geral | M39: =SUM(C36:M36) -> 4462.09
H43: Extrato BB 2025 Ionograma
C45: Janeiro | D45: Fevereiro | E45: Março | F45: Abril | G45: Maio | H45: Junho | I45: Agosto | J45: Setembro | K45: Outubro | L45: Novembro | M45: Dezembro
C46: =Jan!J42 -> 0 | D46: =Fev!J42 -> 0 | E46: =Mar!I41 -> 0 | F46: =Abr!K64 -> 0 | G46: =Mai!K12 -> 3910.44 | H46: 0 | I46: 0 | J46: 0 | K46: 0 | L46: 0 | M46: 0
L49: Geral | M49: =SUM(C46:M46) -> 3910.44

Sheet Jan
A1: Status | B1: Dt. balancete | C1: Ag. origem | D1: Lote | E1: Histórico | F1: Documento | G1: Valor R$ | H1: Observações | J1: =SUBTOTAL(9,Jan!$G$2:$G$618) -> 540014.34
B2: 45657 | C2: 0 | D2: 0 | E2: 000 Saldo Anterior
B3: 45659 | C3: 3525 | D3: 99021 | E3: 870 Transferência recebida | F3: 613525000032047 | G3: 631.8
E4: 02/01 09:49 D&M LABORATORIO DE ANALI
B5: 45659 | C5: 1533 | D5: 99008 | E5: 234 Compra com Cartão | F5: 949158 | G5: 305.71
E6: 02/01 11:37 POSTO SENADOR
B7: 45659 | C7: 0 | D7: 13105 | E7: 109 Pagamento de Boleto | F7: 10201 | G7: 12650.09
E8: APPARAT BRASIL COMERCIO DE REA
B9: 45659 | C9: 0 | D9: 13105 | E9: 109 Pagamento de Boleto | F9: 10202 | G9: 3195.4
E10: TICKET SERVICOS SA
B11: 45659 | C11: 0 | D11: 13105 | E11: 363 Pagto conta telefone | F11: 10203 | G11: 131.01
E12: VIVO RN
B13: 45659 | C13: 0 | D13: 13105 | E13: 109 Pagamento de Boleto | F13: 10204 | G13: 675.6
E14: LABORLAB PROD PARA LAB LTDA
B15: 45659 | C15: 0 | D15: 13105 | E15: 109 Pagamento de Boleto | F15: 10205 | G15: 1392.35
E16: CONFIANCA FUNDO DE INVEST EM D
B17: 45659 | C17: 0 | D17: 13105 | E17: 109 Pagamento de Boleto | F17: 10206 | G17: 686.24
E18: BANCO SOFISA S/A
B19: 45659 | C19: 0 | D19: 13105 | E19: 109 Pagamento de Boleto | F19: 10207 | G19: 1539.04
E20: BIO ADVANCE D LTDA EPP
B21: 45659 | C21: 0 | D21: 13105 | E21: 109 Pagamento de Boleto | F21: 10208 | G21: 1050.34
E22: BIOSYN INDUSTRIA E COMERCIO DE
B23: 45659 | C23: 0 | D23: 13105 | E23: 109 Pagamento de Boleto | F23: 10209 | G23: 283.89
E24: BR COMERCIO DE ELETRONICOS LTD
B25: 45659 | C25: 0 | D25: 13105 | E25: 109 Pagamento de Boleto | F25: 10210 | G25: 256.76
E26: BR COMERCIO DE ELETRONICOS LTD
B27: 45659 | C27: 0 | D27: 13105 | E27: 109 Pagamento de Boleto | F27: 10211 | G27: 233.17
E28: BR COMERCIO DE ELETRONICOS LTD
B29: 45659 | C29: 0 | D29: 13105 | E29: 109 Pagamento de Boleto | F29: 10212 | G29: 204.96
E30: J T A COMERCIO SERVICOS LTDA
B31: 45659 | C31: 0 | D31: 13105 | E31: 109 Pagamento de Boleto | F31: 10213 | G31: 49.9
E32: PJBANK PAGAMENTOS S A_1
B33: 45659 | C33: 0 | D33: 13105 | E33: 109 Pagamento de Boleto | F33: 10214 | G33: 569.46
E34: STER BOM IND. E COM. LTDA
B35: 45659 | C35: 0 | D35: 13105 | E35: 363 Pagto conta telefone | F35: 10215 | G35: 33.43
E36: VIVO RN
B37: 45659 | C37: 0 | D37: 13105 | E37: 109 Pagamento de Boleto | F37: 10216 | G37: 383.86
E38: POLIFARMA DISTRIBUIDORA DE MED
B39: 45659 | C39: 0 | D39: 13105 | E39: 109 Pagamento de Boleto | F39: 10217 | G39: 1553.15
E40: DISTR DE MEDI SANTA CRUZ LTDA
B41: 45659 | C41: 0 | D41: 13105 | E41: 109 Pagamento de Boleto | F41: 10218 | G41: 1877.81
E42: DISTR DE MEDI SANTA CRUZ LTDA
B43: 45659 | C43: 0 | D43: 13105 | E43: 109 Pagamento de Boleto | F43: 10219 | G43: 292.17
E44: DISTR DE MEDI SANTA CRUZ LTDA
B45: 45659 | C45: 0 | D45: 13105 | E45: 109 Pagamento de Boleto | F45: 10220 | G45: 160.03
E46: DISTR DE MEDI SANTA CRUZ LTDA
B47: 45659 | C47: 0 | D47: 13105 | E47: 109 Pagamento de Boleto | F47: 10221 | G47: 92.53
E48: DISTR DE MEDI SANTA CRUZ LTDA
B49: 45659 | C49: 0 | D49: 13105 | E49: 109 Pagamento de Boleto | F49: 10222 | G49: 244.52
E50: COMEBOM DISTRIBUIDORA LTDA
B51: 45659 | C51: 0 | D51: 13105 | E51: 109 Pagamento de Boleto | F51: 10223 | G51: 550.7
E52: POLIFARMA DISTRIBUIDORA DE MED
B53: 45659 | C53: 0 | D53: 13105 | E53: 109 Pagamento de Boleto | F53: 10224 | G53: 375.64
E54: POLIFARMA DISTRIBUIDORA DE MED
B55: 45659 | C55: 0 | D55: 13105 | E55: 109 Pagamento de Boleto | F55: 10225 | G55: 290.13
E56: POLIFARMA DISTRIBUIDORA DE MED
B57: 45659 | C57: 0 | D57: 13105 | E57: 109 Pagamento de Boleto | F57: 10226 | G57: 265.79
E58: RED S A
B59: 45659 | C59: 0 | D59: 13105 | E59: 109 Pagamento de Boleto | F59: 10227 | G59: 284.04
E60: PLENA DISTRIBUIDORA M LTDA
B61: 45659 | C61: 0 | D61: 13105 | E61: 109 Pagamento de Boleto | F61: 10228 | G61: 632.93
E62: PROFARMA DISTRIBUIDORA DE PROD
B63: 45659 | C63: 0 | D63: 13105 | E63: 109 Pagamento de Boleto | F63: 10229 | G63: 481.7
E64: RV TECNOLOGIA S A
B65: 45659 | C65: 0 | D65: 0 | E65: 798 BB Rende Fácil | F65: 9903 | G65: 30110.55
E66: Rende Facil
B67: 45660 | C67: 1533 | D67: 99008 | E67: 234 Compra com Cartão | F67: 757720 | G67: 92.6
E68: 03/01 13:29 AURI ACESSORIOS
B69: 45660 | C69: 0 | D69: 13105 | E69: 109 Pagamento de Boleto | F69: 10301 | G69: 3290.33
E70: BANCO VOLKSWAGEN S.A.
B71: 45660 | C71: 0 | D71: 13105 | E71: 109 Pagamento de Boleto | F71: 10302 | G71: 615.35
E72: DISTR DE MEDI SANTA CRUZ LTDA
B73: 45660 | C73: 0 | D73: 13105 | E73: 109 Pagamento de Boleto | F73: 10303 | G73: 284.35
E74: POLIFARMA DISTRIBUIDORA DE MED
B75: 45660 | C75: 0 | D75: 13105 | E75: 109 Pagamento de Boleto | F75: 10304 | G75: 33.2
E76: NEOENERGIA COSERN
B77: 45660 | C77: 0 | D77: 13105 | E77: 109 Pagamento de Boleto | F77: 10305 | G77: 108.5
E78: NEOENERGIA COSERN
B79: 45660 | C79: 0 | D79: 0 | E79: 798 BB Rende Fácil | F79: 9903 | G79: 4424.33
E80: Rende Facil
B81: 45663 | C81: 0 | D81: 14397 | E81: 821 Pix - Recebido | F81: 361651242544011 | G81: 335.07
E82: 06/01 09:05 02440715000190 LABORATORIO
B83: 45663 | C83: 0 | D83: 0 | E83: 351 BB Rende Fácil | F83: 9903 | G83: 335.07
E84: Rende Facil
B85: 45664 | C85: 1369 | D85: 99015 | E85: 870 Transferência recebida | F85: 551369000138968 | G85: 13
E86: 07/01 08:33 BROKER AUGEFARMA LTDA | G86: 0
B87: 45664 | C87: 5072 | D87: 99021 | E87: 870 Transferência recebida | F87: 615072000004700 | G87: 185.72
E88: 07/01 09:37 S P FH L CLINICO
B89: 45664 | C89: 0 | D89: 14175 | E89: 976 TED-Crédito em Conta | F89: 365430067 | G89: 8900
B90: 45664 | C90: 0 | D90: 14397 | E90: 821 Pix - Recebido | F90: 71557296985222 | G90: 2870
B91: 45664 | C91: 0 | D91: 14397 | E91: 821 Pix - Recebido | F91: 362553708446841 | G91: 957.97
E92: 07/01 10:09 20897601000156 BIO ANALISE | G92: 0
B93: 45664 | C93: 1533 | D93: 99008 | E93: 234 Compra com Cartão | F93: 234224 | G93: 274.06
E94: 07/01 14:29 TM COMBUSTIVEIS | G94: 0
B95: 45664 | C95: 0 | D95: 13105 | E95: 109 Pagamento de Boleto | F95: 10701 | G95: 40.7
E96: RV TECNOLOGIA S A | G96: 0
B97: 45664 | C97: 0 | D97: 13105 | E97: 109 Pagamento de Boleto | F97: 10702 | G97: 3439.38
E98: EBRAM PROD LABORATORIAIS LTDA | G98: 0
B99: 45664 | C99: 0 | D99: 13105 | E99: 109 Pagamento de Boleto | F99: 10703 | G99: 3248
E100: APPARAT BRASIL COMERCIO DE REA | G100: 0
...

Sheet Fev
A1: Status | B1: Dt. balancete | C1: Ag. origem | D1: Lote | E1: Histórico | F1: Documento | G1: Valor R$ | H1: Observações | J1: =SUBTOTAL(9,Fev!$G$2:$G$606) -> 547072.6
B2: 45688 | C2: 0 | D2: 0 | E2: 000 Saldo Anterior
B3: 45691 | C3: 1845 | D3: 99021 | E3: 870 Transferência recebida | F3: 611845000040070 | G3: 1015.98
E4: 03/02 08:09 RP SERVICOS LABORATORIAI
B5: 45691 | C5: 0 | D5: 14175 | E5: 976 TED-Crédito em Conta | F5: 368466185 | G5: 6000
E6: 748 2207 03319496000159 MEDCAL FARMA H
B7: 45691 | C7: 0 | D7: 13105 | E7: 109 Pagamento de Boleto | F7: 20301 | G7: 339.9
E8: RV TECNOLOGIA S A
B9: 45691 | C9: 0 | D9: 13105 | E9: 375 Impostos | F9: 20302 | G9: 1907.51
E10: RN TRIBUTACAO ICMS
B11: 45691 | C11: 0 | D11: 13105 | E11: 375 Impostos | F11: 20303 | G11: 23.55
E12: RN TRIBUTACAO ICMS
B13: 45691 | C13: 0 | D13: 13105 | E13: 363 Pagto conta telefone | F13: 20304 | G13: 957.81
E14: TIM S/A
B15: 45691 | C15: 0 | D15: 13105 | E15: 109 Pagamento de Boleto | F15: 20305 | G15: 49.9
E16: PJBANK PAGAMENTOS S A_1
B17: 45691 | C17: 0 | D17: 13105 | E17: 109 Pagamento de Boleto | F17: 20306 | G17: 3216.46
E18: EBRAM PROD LABORATORIAIS LTDA
B19: 45691 | C19: 0 | D19: 13105 | E19: 109 Pagamento de Boleto | F19: 20307 | G19: 450.76
E20: DISTR DE MEDI SANTA CRUZ LTDA
B21: 45691 | C21: 0 | D21: 13105 | E21: 109 Pagamento de Boleto | F21: 20308 | G21: 33.73
E22: DISTR DE MEDI SANTA CRUZ LTDA
B23: 45691 | C23: 0 | D23: 13105 | E23: 109 Pagamento de Boleto | F23: 20309 | G23: 1145.18
E24: DPC DISTRIBUIDOR ATACADISTA S
B25: 45691 | C25: 0 | D25: 0 | E25: 798 BB Rende Fácil | F25: 9903 | G25: 1108.82
E26: Rende Facil
B27: 45692 | C27: 0 | D27: 14397 | E27: 821 Pix - Recebido | F27: 41337405446532 | G27: 2000
E28: 04/02 13:37 03319496000159 MEDCAL FARM
A29: Baixado | B29: 45692 | C29: 0 | D29: 14138 | E29: 632 Ordem Bancária | F29: 202502030059176 | G29: 2877.71 | H29: FATURA 3191.1 CONJUNTO DE SOLU ES,RE
E30: ESTADO DO RIO GRANDE D
A31: Baixado | B31: 45692 | C31: 0 | D31: 14138 | E31: 632 Ordem Bancária | F31: 202502030059178 | G31: 1232.84 | H31: FATURA 3191.1 CONJUNTO DE SOLU ES,RE
E32: ESTADO DO RIO GRANDE D
A33: Baixado | B33: 45692 | C33: 0 | D33: 14138 | E33: 632 Ordem Bancária | F33: 202502030059180 | G33: 804.25 | H33: FATURA 3272.1 COMP. 12 24 - CONJUNTO
E34: ESTADO DO RIO GRANDE D
A35: Baixado | B35: 45692 | C35: 0 | D35: 14138 | E35: 632 Ordem Bancária | F35: 202502030059182 | G35: 1668.08 | H35: FATURA 3272.1 COMP. 12 24 - CONJUNTO
E36: ESTADO DO RIO GRANDE D
A37: Baixado | B37: 45692 | C37: 0 | D37: 14138 | E37: 632 Ordem Bancária | F37: 202502030059188 | G37: 9096.92 | H37: FTs 3261 e 3240 - COMP 12 2024, ref. ao
E38: ESTADO DO RIO GRANDE D
B39: 45692 | C39: 0 | D39: 13105 | E39: 375 Impostos | F39: 20401 | G39: 175.72
E40: RN TRIBUTACAO ICMS
B41: 45692 | C41: 0 | D41: 13105 | E41: 109 Pagamento de Boleto | F41: 20402 | G41: 1518
E42: OLIMPUS TECNOLOGIA EM SISTEMAS
B43: 45692 | C43: 0 | D43: 13105 | E43: 109 Pagamento de Boleto | F43: 20403 | G43: 6324.55
E44: LABOR IMPORT COMERCIAL IMPORTA
B45: 45692 | C45: 0 | D45: 13105 | E45: 109 Pagamento de Boleto | F45: 20404 | G45: 3248
E46: APPARAT BRASIL COMERCIO DE REA
B47: 45692 | C47: 0 | D47: 13105 | E47: 109 Pagamento de Boleto | F47: 20405 | G47: 1110
E48: APPARAT BRASIL C R I LTDA
B49: 45692 | C49: 0 | D49: 13105 | E49: 109 Pagamento de Boleto | F49: 20406 | G49: 2209.86
E50: EBRAM PROD LABORATORIAIS LTDA
B51: 45692 | C51: 0 | D51: 13105 | E51: 109 Pagamento de Boleto | F51: 20407 | G51: 562.38
E52: POLIFARMA DISTRIBUIDORA DE MED
B53: 45692 | C53: 0 | D53: 13105 | E53: 109 Pagamento de Boleto | F53: 20408 | G53: 266.25
E54: POLIFARMA DISTRIBUIDORA DE MED
B55: 45692 | C55: 0 | D55: 13105 | E55: 109 Pagamento de Boleto | F55: 20409 | G55: 399.08
E56: POLIFARMA DISTRIBUIDORA DE MED
B57: 45692 | C57: 0 | D57: 13105 | E57: 109 Pagamento de Boleto | F57: 20410 | G57: 257.21
E58: POLIFARMA DISTRIBUIDORA DE MED
B59: 45692 | C59: 0 | D59: 13105 | E59: 109 Pagamento de Boleto | F59: 20411 | G59: 235.16
E60: POLIFARMA DISTRIBUIDORA DE MED
B61: 45692 | C61: 0 | D61: 13105 | E61: 109 Pagamento de Boleto | F61: 20412 | G61: 29.41
E62: DISTR DE MEDI SANTA CRUZ LTDA
B63: 45692 | C63: 0 | D63: 13105 | E63: 109 Pagamento de Boleto | F63: 20413 | G63: 247.62
E64: ACRIPEL DISTRIBUIDORA PERNAMBU
B65: 45692 | C65: 0 | D65: 13105 | E65: 109 Pagamento de Boleto | F65: 20414 | G65: 250.88
E66: PROFARMA
B67: 45692 | C67: 0 | D67: 13105 | E67: 109 Pagamento de Boleto | F67: 20415 | G67: 516.1
E68: PROFARMA
B69: 45692 | C69: 0 | D69: 13105 | E69: 109 Pagamento de Boleto | F69: 20416 | G69: 252.21
E70: PROFARMA
B71: 45692 | C71: 0 | D71: 0 | E71: 351 BB Rende Fácil | F71: 9903 | G71: 77.37
E72: Rende Facil
B73: 45693 | C73: 1106 | D73: 99015 | E73: 870 Transferência recebida | F73: 551106000031574 | G73: 12117.57 | H73: Parelhas
E74: 05/02 15:18 FUNDO MUNICIPAL DE SAUDE
B75: 45693 | C75: 0 | D75: 14175 | E75: 976 TED-Crédito em Conta | F75: 368920293 | G75: 9500
E76: 748 2207 03319496000159 MEDCAL FARMA H
B77: 45693 | C77: 0 | D77: 14397 | E77: 821 Pix - Recebido | F77: 51543390726822 | G77: 130
E78: 05/02 15:43 00007945263496 EGSTON FELI
B79: 45693 | C79: 0 | D79: 14397 | E79: 821 Pix - Recebido | F79: 387835653088721 | G79: 203.55
E80: 05/02 16:26 40784407000171 CENTRO CLIN
B81: 45693 | C81: 0 | D81: 13105 | E81: 375 Impostos | F81: 20501 | G81: 42.53
E82: RN TRIBUTACAO ICMS
B83: 45693 | C83: 0 | D83: 13105 | E83: 375 Impostos | F83: 20502 | G83: 246.64
E84: RN TRIBUTACAO ICMS
B85: 45693 | C85: 0 | D85: 13105 | E85: 375 Impostos | F85: 20503 | G85: 578.29
E86: RN TRIBUTACAO ICMS
B87: 45693 | C87: 0 | D87: 13105 | E87: 109 Pagamento de Boleto | F87: 20504 | G87: 5511.43
E88: APPARAT BRASIL COMERCIO DE REA
B89: 45693 | C89: 0 | D89: 13105 | E89: 109 Pagamento de Boleto | F89: 20505 | G89: 1418
E90: APPARAT BRASIL C R I LTDA
B91: 45693 | C91: 0 | D91: 13105 | E91: 109 Pagamento de Boleto | F91: 20506 | G91: 173.35
E92: SISMETRO UPSIM SISTEMAS LTDA
B93: 45693 | C93: 0 | D93: 13105 | E93: 109 Pagamento de Boleto | F93: 20507 | G93: 780.96
E94: AGENCIA NACIONAL DE VIGILANCIA
B95: 45693 | C95: 0 | D95: 13105 | E95: 109 Pagamento de Boleto | F95: 20508 | G95: 250.88
E96: PROFARMA
B97: 45693 | C97: 0 | D97: 13105 | E97: 109 Pagamento de Boleto | F97: 20509 | G97: 327.78
E98: ACRIPEL DISTRIBUIDORA PERNAMBU
B99: 45693 | C99: 0 | D99: 13105 | E99: 109 Pagamento de Boleto | F99: 20510 | G99: 3361.99
E100: BANCO VOLKSWAGEN S.A.
...

Sheet Mar
A1: Status | B1: Dt. balancete | C1: Ag. origem | D1: Lote | E1: Histórico | F1: Documento | G1: Valor R$ | H1: TOTAL | I1: =SUBTOTAL(9,Mar!$G$2:$G$478) -> 354538.76
B2: 45721 | C2: 0 | D2: 14175 | E2: 976 TED-Crédito em Conta | F2: 372406878 | G2: 5000
E3: 748 2207 03319496000159 MEDCAL FARMA H | G3: 0
A4: Baixado | B4: 45721 | C4: 0 | D4: 14138 | E4: 632 Ordem Bancária | F4: 202502280062948 | G4: 1024.16 | H4: 3263
E5: ESTADO DO RIO GRANDE D | G5: 0
A6: Baixado | B6: 45721 | C6: 0 | D6: 14138 | E6: 632 Ordem Bancária | F6: 202502280062949 | G6: 1668.08 | H6: 3239
E7: ESTADO DO RIO GRANDE D | G7: 0
B8: 45721 | C8: 1533 | D8: 99008 | E8: 234 Compra com Cartão | F8: 91862 | G8: 227.3
E9: 03/03 20:05 POSTO DINIZ - EMAUS | G9: 0
B10: 45721 | C10: 0 | D10: 13105 | E10: 109 Pagamento de Boleto | F10: 30501 | G10: 49.9
E11: PJBANK PAGAMENTOS S A_1 | G11: 0
B12: 45721 | C12: 0 | D12: 13105 | E12: 109 Pagamento de Boleto | F12: 30502 | G12: 736.36
E13: APPARAT BRASIL C R I LTDA | G13: 0
B14: 45721 | C14: 0 | D14: 13105 | E14: 109 Pagamento de Boleto | F14: 30503 | G14: 187.2
E15: CRIL EMPREENDIMENTO AMBIENTAL | G15: 0
B16: 45721 | C16: 0 | D16: 13105 | E16: 109 Pagamento de Boleto | F16: 30504 | G16: 393.58
E17: KATAL BIOTECNOLOGICA INDUSTRIA | G17: 0
B18: 45721 | C18: 0 | D18: 13105 | E18: 109 Pagamento de Boleto | F18: 30505 | G18: 2282.77
E19: KATAL BIOTECNOLOGICA INDUSTRIA | G19: 0
B20: 45721 | C20: 0 | D20: 13105 | E20: 109 Pagamento de Boleto | F20: 30506 | G20: 817.82
E21: MEDIARTE COMERCIO E SERVICOS D | G21: 0
B22: 45721 | C22: 0 | D22: 13105 | E22: 109 Pagamento de Boleto | F22: 30507 | G22: 305.44
E23: STER BOM IND. E COM. LTDA | G23: 0
B24: 45721 | C24: 0 | D24: 13105 | E24: 109 Pagamento de Boleto | F24: 30508 | G24: 392.62
E25: STER BOM IND. E COM. LTDA | G25: 0
B26: 45721 | C26: 0 | D26: 13105 | E26: 109 Pagamento de Boleto | F26: 30509 | G26: 2617.4
E27: TICKET SERVICOS SA | G27: 0
B28: 45721 | C28: 0 | D28: 13105 | E28: 109 Pagamento de Boleto | F28: 30510 | G28: 158.3
E29: RV TECNOLOGIA S A | G29: 0
B30: 45721 | C30: 0 | D30: 0 | E30: 798 BB Rende Fácil | F30: 9903 | G30: 476.45
E31: Rende Facil | G31: 0
B32: 45722 | C32: 128 | D32: 99021 | E32: 870 Transferência recebida | F32: 610128000064860 | G32: 2264.76
E33: 06/03 11:01 CLINICA CLINCORDIS | G33: 0
B34: 45722 | C34: 0 | D34: 14397 | E34: 821 Pix - Recebido | F34: 60925331558762 | G34: 105.6
E35: 06/03 09:25 17135621000185 PET SHOP RE | G35: 0
B36: 45722 | C36: 0 | D36: 14397 | E36: 821 Pix - Recebido | F36: 61003344259782 | G36: 1270
E37: 06/03 10:03 03319496000159 MEDCAL FARM | G37: 0
B38: 45722 | C38: 0 | D38: 14397 | E38: 821 Pix - Recebido | F38: 61544237632392 | G38: 170
E39: 06/03 15:44 00070250037432 BRUNO GABRI | G39: 0
B40: 45722 | C40: 1533 | D40: 99008 | E40: 234 Compra com Cartão | F40: 588893 | G40: 238.72
E41: 06/03 12:14 POSTO COSTINHA V | G41: 0
B42: 45722 | C42: 0 | D42: 13105 | E42: 109 Pagamento de Boleto | F42: 30601 | G42: 217.1
E43: RV TECNOLOGIA S A | G43: 0
B44: 45722 | C44: 0 | D44: 13105 | E44: 375 Impostos | F44: 30602 | G44: 73.57
E45: RN TRIBUTACAO ICMS | G45: 0
B46: 45722 | C46: 0 | D46: 13105 | E46: 109 Pagamento de Boleto | F46: 30603 | G46: 243.55
E47: FARMAUM NATAL M LTDA | G47: 0
B48: 45722 | C48: 0 | D48: 13105 | E48: 109 Pagamento de Boleto | F48: 30604 | G48: 265.05
E49: ACRIPEL DISTRIBUIDORA PERNAMBU | G49: 0
B50: 45722 | C50: 0 | D50: 13105 | E50: 109 Pagamento de Boleto | F50: 30605 | G50: 197.49
E51: ACRIPEL DISTRIBUIDORA PERNAMBU | G51: 0
B52: 45722 | C52: 0 | D52: 0 | E52: 351 BB Rende Fácil | F52: 9903 | G52: 2574.88
E53: Rende Facil | G53: 0
B54: 45723 | C54: 5072 | D54: 99021 | E54: 870 Transferência recebida | F54: 615072000004700 | G54: 314.85
E55: 07/03 13:10 S P FH L CLINICO | G55: 0
B56: 45723 | C56: 0 | D56: 14175 | E56: 976 TED-Pag Fornecedores | F56: 34033291 | G56: 2073
E57: 104 7853 10709689000181 FUNDO DE SAUDE | G57: 0
B58: 45723 | C58: 0 | D58: 14397 | E58: 821 Pix - Recebido | F58: 71053360317352 | G58: 3000
E59: 07/03 10:53 13640653000187 S O SERV SA | G59: 0
B60: 45723 | C60: 0 | D60: 14397 | E60: 821 Pix - Recebido | F60: 71128070461482 | G60: 1728
E61: 07/03 11:28 09127333000150 ASSISTENCIA | G61: 0
B62: 45723 | C62: 0 | D62: 14397 | E62: 821 Pix - Recebido | F62: 71932300235532 | G62: 2200
E63: 07/03 19:32 41109772000143 MAIS SAUDE | G63: 0
B64: 45723 | C64: 1533 | D64: 99008 | E64: 234 Compra com Cartão | F64: 699977 | G64: 308.91
E65: 07/03 21:40 POSTO DINIZ - EMAUS | G65: 0
B66: 45723 | C66: 1533 | D66: 99015 | E66: 470 Transferência enviada | F66: 551845000113366 | G66: 3442.72
E67: 07/03 17:06 JONATAN EDUARDO M SILVA | G67: 0
B68: 45723 | C68: 0 | D68: 13105 | E68: 109 Pagamento de Boleto | F68: 30701 | G68: 122.38
E69: DISTR DE MEDI SANTA CRUZ LTDA | G69: 0
B70: 45723 | C70: 0 | D70: 13105 | E70: 109 Pagamento de Boleto | F70: 30702 | G70: 1225.99
E71: Sanafarma Industria E Comercio | G71: 0
B72: 45723 | C72: 0 | D72: 13105 | E72: 109 Pagamento de Boleto | F72: 30703 | G72: 1418
E73: APPARAT BRASIL C R I LTDA | G73: 0
B74: 45723 | C74: 0 | D74: 13105 | E74: 109 Pagamento de Boleto | F74: 30704 | G74: 337
E75: APPARAT BRASIL C R I LTDA | G75: 0
B76: 45723 | C76: 0 | D76: 13105 | E76: 375 Impostos | F76: 30705 | G76: 132.31
E77: RN TRIBUTACAO ICMS | G77: 0
B78: 45723 | C78: 0 | D78: 13105 | E78: 375 Impostos | F78: 30706 | G78: 791.09
E79: RN TRIBUTACAO ICMS | G79: 0
B80: 45723 | C80: 0 | D80: 13105 | E80: 109 Pagamento de Boleto | F80: 30707 | G80: 2022.45
E81: PONTELAND DISTRIBUICAO S.A. | G81: 0
B82: 45723 | C82: 0 | D82: 13113 | E82: 435 Tarifa Pacote de Serviços | F82: 890661200446460 | G82: 75.4
E83: Cobrança referente 07/03/2025 | G83: 0
B84: 45723 | C84: 0 | D84: 0 | E84: 798 BB Rende Fácil | F84: 9903 | G84: 560.4
E85: Rende Facil | G85: 0
B86: 45726 | C86: 984 | D86: 99015 | E86: 870 Transferência recebida | F86: 550984000024887 | G86: 2665.6 | H86: Santa Maria
E87: 10/03 16:55 FMS SANTA MARIA RN FUS | G87: 0
B88: 45726 | C88: 0 | D88: 14397 | E88: 821 Pix - Recebido | F88: 101043428124392 | G88: 675.04
E89: 10/03 10:43 08075247000189 UNNIQUE C L | G89: 0
B90: 45726 | C90: 0 | D90: 14397 | E90: 821 Pix - Recebido | F90: 101059353965112 | G90: 1679.93
E91: 10/03 10:59 08075247000189 UNNIQUE C L | G91: 0
B92: 45726 | C92: 0 | D92: 14397 | E92: 821 Pix - Recebido | F92: 101409355108202 | G92: 69.9
E93: 10/03 14:09 21709133000101 LABORATORIO | G93: 0
B94: 45726 | C94: 0 | D94: 14397 | E94: 821 Pix - Recebido | F94: 102117221158722 | G94: 1808
E95: 10/03 21:17 17135621000185 E L SALGUEI | G95: 0
B96: 45726 | C96: 0 | D96: 14397 | E96: 821 Pix - Recebido | F96: 416145253276381 | G96: 2523.89
E97: 10/03 10:48 08075247000189 UNNIQUE C L | G97: 0
B98: 45726 | C98: 0 | D98: 14397 | E98: 821 Pix - Recebido | F98: 416146037857701 | G98: 850
E99: 10/03 10:50 03319496000230 Medcal Farm | G99: 0
B100: 45726 | C100: 0 | D100: 13105 | E100: 109 Pagamento de Boleto | F100: 31001 | G100: 378.61
...

Sheet Abr
A1: Status | B1: Dt. balancete | C1: Ag. origem | D1: Lote | E1: Histórico | F1: Documento | G1: Valor R$ | H1: Fatura | I1: Tipo | J1: Hematologia = | K1: =SUMIF(I60:I843,"Hematologia", G60:G843) -> 88043.08 | L1: TOTAL = | M1: =SUBTOTAL(9,Abr!$G$2:$G$889) -> 786969.58
B2: 45747 | C2: 0 | D2: 0 | E2: 000 Saldo Anterior | G2: 0
B3: 45748 | C3: 0 | D3: 14175 | E3: 976 TED-Crédito em Conta | F3: 376064205 | G3: 1170
E4: 748 2207 03319496000159 MEDCAL FARMA H | G4: 0
B5: 45748 | C5: 0 | D5: 14397 | E5: 821 Pix - Recebido | F5: 11508273488002 | G5: 6500
E6: 01/04 15:08 32958432000104 SLE SERVICO | G6: 0
B7: 45748 | C7: 0 | D7: 14397 | E7: 821 Pix - Recebido | F7: 435338422459261 | G7: 299.82
E8: 01/04 15:57 01751313417 Nathaly Dandar | G8: 0
B9: 45748 | C9: 0 | D9: 14397 | E9: 821 Pix - Recebido | F9: 435557650544891 | G9: 3200
E10: 01/04 22:02 01692863479 ANDERSON V OLI | G10: 0
B11: 45748 | C11: 0 | D11: 13105 | E11: 109 Pagamento de Boleto | F11: 40101 | G11: 233.6
E12: RV TECNOLOGIA S A | G12: 0
B13: 45748 | C13: 0 | D13: 13105 | E13: 109 Pagamento de Boleto | F13: 40102 | G13: 94.6
E14: RV TECNOLOGIA S A | G14: 0
B15: 45748 | C15: 0 | D15: 13105 | E15: 109 Pagamento de Boleto | F15: 40103 | G15: 816.83
E16: MEDIARTE COMERCIO E SERVICOS D | G16: 0
B17: 45748 | C17: 0 | D17: 13105 | E17: 375 Impostos | F17: 40104 | G17: 1749.69
E18: RN TRIBUTACAO ICMS | G18: 0
B19: 45748 | C19: 0 | D19: 13105 | E19: 375 Impostos | F19: 40105 | G19: 927.23
E20: RN TRIBUTACAO ICMS | G20: 0
B21: 45748 | C21: 0 | D21: 13105 | E21: 109 Pagamento de Boleto | F21: 40106 | G21: 3802.32
E22: BANCO ITAUCARD S.A. | G22: 0
B23: 45748 | C23: 0 | D23: 13105 | E23: 109 Pagamento de Boleto | F23: 40107 | G23: 49.9
E24: PJBANK PAGAMENTOS S A_1 | G24: 0
B25: 45748 | C25: 0 | D25: 0 | E25: 351 BB Rende Fácil | F25: 9903 | G25: 3495.65
E26: Rende Facil | G26: 0
B27: 45749 | C27: 2084 | D27: 99021 | E27: 870 Transferência recebida | F27: 612084000112119 | G27: 1250
B28: 45749 | C28: 0 | D28: 14175 | E28: 976 TED-Crédito em Conta | F28: 376225160 | G28: 1000
E29: 748 2207 03319496000159 MEDCAL FARMA H | G29: 0
B30: 45749 | C30: 0 | D30: 14397 | E30: 821 Pix - Recebido | F30: 21004434335392 | G30: 1124.35
E31: 02/04 10:04 11006454000196 LAB DE ANAL | G31: 0
B32: 45749 | C32: 0 | D32: 14397 | E32: 821 Pix - Recebido | F32: 21540276072622 | G32: 587.39
E33: 02/04 15:40 28155001000396 CLINICA SAN | G33: 0
B34: 45749 | C34: 0 | D34: 14397 | E34: 821 Pix - Recebido | F34: 435913651776191 | G34: 300
E35: 02/04 07:56 01692863479 ANDERSON V OLI | G35: 0
B36: 45749 | C36: 0 | D36: 14397 | E36: 821 Pix - Recebido | F36: 436279502192591 | G36: 3000
E37: 02/04 18:05 13640653000187 SILVA & OLI | G37: 0
B38: 45749 | C38: 1533 | D38: 99008 | E38: 234 Compra com Cartão | F38: 220617 | G38: 216.61
E39: 02/04 08:31 POSTO DINIZ - EMAUS | G39: 0
B40: 45749 | C40: 1533 | D40: 99008 | E40: 234 Compra com Cartão | F40: 965773 | G40: 120
E41: 02/04 15:36 L E L MATRIX COM DE | G41: 0
B42: 45749 | C42: 0 | D42: 13105 | E42: 109 Pagamento de Boleto | F42: 40201 | G42: 3544.18
E43: EBRAM PROD LABORATORIAIS LTDA | G43: 0
B44: 45749 | C44: 0 | D44: 13105 | E44: 109 Pagamento de Boleto | F44: 40202 | G44: 562.77
E45: STER BOM IND. E COM. LTDA | G45: 0
B46: 45749 | C46: 0 | D46: 13105 | E46: 109 Pagamento de Boleto | F46: 40203 | G46: 559.88
E47: CIMED CO. S.A | G47: 0
B48: 45749 | C48: 0 | D48: 13105 | E48: 109 Pagamento de Boleto | F48: 40204 | G48: 396.6
E49: CIMED CO S A | G49: 0
B50: 45749 | C50: 0 | D50: 13105 | E50: 109 Pagamento de Boleto | F50: 40205 | G50: 91.61
E51: NEOENERGIA COSERN | G51: 0
B52: 45749 | C52: 0 | D52: 13105 | E52: 109 Pagamento de Boleto | F52: 40206 | G52: 108.78
E53: NEOENERGIA COSERN | G53: 0
B54: 45749 | C54: 0 | D54: 0 | E54: 351 BB Rende Fácil | F54: 9903 | G54: 1661.31
E55: Rende Facil | G55: 0
B56: 45750 | C56: 2035 | D56: 99015 | E56: 870 Transferência recebida | F56: 552035000900025 | G56: 7775.52
E57: 03/04 13:31 INSTITUTO ISSERN | G57: 0
B58: 45750 | C58: 984 | D58: 99021 | E58: 870 Transferência recebida | F58: 610984000009994 | G58: 187.18
E59: 03/04 15:38 LABORATORIO LAPAC LTDA | G59: 0
A60: Baixado | B60: 45750 | C60: 0 | D60: 14138 | E60: 632 Ordem Bancária | F60: 202504020000023 | G60: 238 | H60: 2770 | I60: Coagulação | J60: Coagulação = | K60: =SUMIF(I60:I843,"Coagulação",G60:G843) -> 10125.28 | L60: Baixado | M60: =SUMIF(A:A,"Baixado",G:G) -> 124914.99
E61: ESTADO DO RIO GRANDE D | G61: 0 | K61: =SUMIF(I61:I844,"Coagulação",G61:G844) -> 9887.28
A62: Baixado | B62: 45750 | C62: 0 | D62: 14138 | E62: 632 Ordem Bancária | F62: 202504020000026 | G62: 238 | H62: 3003 | I62: Coagulação | J62: TT/TTPA = | K62: =SUMIF(I62:I845,"TT/TTPA",G62:G845) -> 4462.09 | L62: Pendente | M62: =SUMIF(A:A,"Pendente",G:G) -> 20067.32
E63: ESTADO DO RIO GRANDE D | G63: 0 | K63: =SUMIF(I63:I846,"TT/TTPA",G63:G846) -> 4462.09
A64: Baixado | B64: 45750 | C64: 0 | D64: 14138 | E64: 632 Ordem Bancária | F64: 202504020000027 | G64: 238 | H64: 3001 | I64: Coagulação | J64: Ionograma = | K64: =SUMIF(I64:I847,"Ionograma",G64:G847) -> 0
E65: ESTADO DO RIO GRANDE D | G65: 0
A66: Baixado | B66: 45750 | C66: 0 | D66: 14138 | E66: 632 Ordem Bancária | F66: 202504020000028 | G66: 609.28 | H66: 3102 | I66: Coagulação
E67: ESTADO DO RIO GRANDE D | G67: 0
A68: Pendente | B68: 45750 | C68: 0 | D68: 14138 | E68: 632 Ordem Bancária | F68: 202504020000029 | G68: 14.22 | H68: 3142 | I68: TT/TTPA | J68: Valor da nota R$ 149,35
E69: ESTADO DO RIO GRANDE D | G69: 0
A70: Baixado | B70: 45750 | C70: 0 | D70: 14138 | E70: 632 Ordem Bancária | F70: 202504020014990 | G70: 3336.17 | H70: 3305 e 3383 | I70: Hematologia
E71: ESTADO DO RIO GRANDE D | G71: 0
B72: 45750 | C72: 0 | D72: 14397 | E72: 821 Pix - Recebido | F72: 437122630208911 | G72: 1400
E73: 03/04 17:31 03319496000159 Medcal Farm | G73: 0
B74: 45750 | C74: 1533 | D74: 99008 | E74: 234 Compra com Cartão | F74: 828268 | G74: 187.76
E75: 03/04 17:36 TM COMBUSTIVEIS | G75: 0
B76: 45750 | C76: 0 | D76: 13105 | E76: 363 Pagto conta telefone | F76: 40301 | G76: 985.27
E77: TIM S/A | G77: 0
B78: 45750 | C78: 0 | D78: 13105 | E78: 109 Pagamento de Boleto | F78: 40302 | G78: 1339.21
E79: EBRAM PROD LABORATORIAIS LTDA | G79: 0
B80: 45750 | C80: 0 | D80: 13105 | E80: 109 Pagamento de Boleto | F80: 40303 | G80: 3654.74
E81: EBRAM PROD LABORATORIAIS LTDA | G81: 0
B82: 45750 | C82: 0 | D82: 0 | E82: 351 BB Rende Fácil | F82: 9903 | G82: 7869.39
E83: Rende Facil | G83: 0
B84: 45751 | C84: 4833 | D84: 74680 | E84: 830 Dep dinheiro ATM | F84: 483374680150116 | G84: 500
E85: 04/04 15:01 SOP-PONTA NEGRA | G85: 0
B86: 45751 | C86: 0 | D86: 14175 | E86: 976 TED-Crédito em Conta | F86: 376719199 | G86: 23000
E87: 748 2207 03319496000159 MEDCAL FARMA H | G87: 0
B88: 45751 | C88: 0 | D88: 14397 | E88: 821 Pix - Recebido | F88: 40924247471092 | G88: 232.75
E89: 04/04 09:24 00037891987491 SILVAN SOUZ | G89: 0
A90: Baixado | B90: 45751 | C90: 0 | D90: 14138 | E90: 632 Ordem Bancária | F90: 202504030005002 | G90: 1633.63 | H90: 3375 e 3455 | I90: Hematologia
E91: ESTADO DO RIO GRANDE D | G91: 0
A92: Baixado | B92: 45751 | C92: 0 | D92: 14138 | E92: 632 Ordem Bancária | F92: 202504030016797 | G92: 3362.94 | H92: Maria Alice NF 3468 | I92: Hematologia
E93: ESTADO DO RIO GRANDE D | G93: 0
B94: 45751 | C94: 1533 | D94: 99008 | E94: 234 Compra com Cartão | F94: 74147 | G94: 152.8
E95: 04/04 21:03 POSTO BRILHANTAO LTD | G95: 0
B96: 45751 | C96: 0 | D96: 13105 | E96: 109 Pagamento de Boleto | F96: 40401 | G96: 2846.8
E97: CONFIANCA FUNDO DE INVEST EM D | G97: 0
B98: 45751 | C98: 0 | D98: 13105 | E98: 109 Pagamento de Boleto | F98: 40402 | G98: 2214.98
E99: CONFIANCA FUNDO DE INVEST EM D | G99: 0
B100: 45751 | C100: 0 | D100: 13105 | E100: 109 Pagamento de Boleto | F100: 40403 | G100: 1286.7
...

Sheet Mai
A1: Status | B1: Dt. balancete | C1: Ag. origem | D1: Lote | E1: Histórico | F1: Documento | G1: Valor R$ | H1: Fatura | I1: Tipo | J1: Hematologia = | K1: =SUMIF(I8:I1067,"Hematologia", G8:G1098) -> 162800.05 | L1: Total = | M1: =SUBTOTAL(9,Mai!$G$2:$G$1098) -> 828438.8
B2: 45779 | C2: 0 | D2: 14175 | E2: 976 TED-Crédito em Conta | F2: 379709184 | G2: 5500 | H2: Medcal P/ Medcal via sicred
E3: 748 2207 03319496000159 MEDCAL FARMA H | G3: 0 | K3: =SUMIF(I10:I1069,"Hematologia", G10:G1069) -> 160895.3
B4: 45779 | C4: 0 | D4: 14397 | E4: 821 Pix - Recebido | F4: 21315345571562 | G4: 526.08
E5: 02/05 13:15 09522383000132 CENTRO A C | G5: 0 | K5: =SUMIF(I12:I1071,"Hematologia", G12:G1071) -> 160591.61
B6: 45779 | C6: 0 | D6: 14397 | E6: 821 Pix - Recebido | F6: 21445329484242 | G6: 45
E7: 02/05 14:45 00001692863479 ANDERSON V | G7: 0 | K7: =SUMIF(I14:I1073,"Hematologia", G14:G1073) -> 158923.53
A8: Baixado | B8: 45779 | C8: 0 | D8: 14138 | E8: 632 Ordem Bancária | F8: 202504300023214 | G8: 1904.75 | H8: 3168 e 3211 | I8: Hematologia | J8: Coagulação = | K8: =SUMIF(I8:I1067,"Coagulação", G8:G1067) -> 22726.57 | L8: Baixado = | M8: =SUMIF(A:A,"Baixado",G:G) -> 227636.03
E9: ESTADO DO RIO GRANDE D | G9: 0 | K9: =SUMIF(I16:I1075,"Hematologia", G16:G1075) -> 158923.53
A10: Baixado | B10: 45779 | C10: 0 | D10: 14138 | E10: 632 Ordem Bancária | F10: 202504300023219 | G10: 303.69 | H10: 3535 | I10: Hematologia | J10: TT/TTPA = | K10: =SUMIF(I8:I1060,"TT/TTPA", G8:G1067) -> 0 | L10: Pendente = | M10: =SUMIF(A:A,"Pendente",G:G) -> 0
E11: ESTADO DO RIO GRANDE D | G11: 0 | K11: =SUMIF(I18:I1077,"Hematologia", G18:G1077) -> 158923.53
A12: Baixado | B12: 45779 | C12: 0 | D12: 14138 | E12: 632 Ordem Bancária | F12: 202504300023227 | G12: 1668.08 | H12: 3487 | I12: Hematologia | J12: Ionograma = | K12: =SUMIF(I8:I1067,"Ionograma", G8:G1067) -> 3910.44
E13: ESTADO DO RIO GRANDE D | G13: 0
B14: 45779 | C14: 0 | D14: 14397 | E14: 821 Pix - Recebido | F14: 461924463784051 | G14: 299.34
E15: 02/05 10:27 12644969000184 I M M VAREL | G15: 0
B16: 45779 | C16: 0 | D16: 14397 | E16: 821 Pix - Recebido | F16: 461959284912981 | G16: 95
E17: 02/05 11:25 14054616000150 MAFALDO & S | G17: 0
B18: 45779 | C18: 0 | D18: 14397 | E18: 821 Pix - Recebido | F18: 462016847829531 | G18: 526.08
E19: 02/05 13:01 01850297444 JOSE DO EGITO | G19: 0
B20: 45779 | C20: 0 | D20: 14397 | E20: 821 Pix - Recebido | F20: 462151663820241 | G20: 3000
E21: 02/05 16:46 02400158436 João Hélio Oli | G21: 0
B22: 45779 | C22: 1533 | D22: 99008 | E22: 234 Compra com Cartão | F22: 14870 | G22: 102.09
E23: 02/05 16:07 FLOR E OLIVEIRA LTDA | G23: 0
B24: 45779 | C24: 1533 | D24: 99008 | E24: 234 Compra com Cartão | F24: 332442 | G24: 203.73
E25: 02/05 11:26 BRASIL EMBALAGEM | G25: 0
B26: 45779 | C26: 0 | D26: 13105 | E26: 109 Pagamento de Boleto | F26: 50201 | G26: 380.44
E27: BIONEXO S A | G27: 0
B28: 45779 | C28: 0 | D28: 13105 | E28: 109 Pagamento de Boleto | F28: 50202 | G28: 337.25
E29: AIRSUPPLY LOGISTICA T LTDA | G29: 0
B30: 45779 | C30: 0 | D30: 13105 | E30: 109 Pagamento de Boleto | F30: 50203 | G30: 1236.86
E31: BIOSUL PRODUTOS DIAGNOSTICOS L | G31: 0
B32: 45779 | C32: 0 | D32: 13105 | E32: 109 Pagamento de Boleto | F32: 50204 | G32: 1056
E33: Sanafarma Industria E Comercio | G33: 0
B34: 45779 | C34: 0 | D34: 13105 | E34: 109 Pagamento de Boleto | F34: 50205 | G34: 999.75
E35: BIOSYN INDUSTRIA E COMERCIO DE | G35: 0
B36: 45779 | C36: 0 | D36: 13105 | E36: 109 Pagamento de Boleto | F36: 50206 | G36: 2677.13
E37: EBRAM PROD LABORATORIAIS LTDA | G37: 0
B38: 45779 | C38: 0 | D38: 13105 | E38: 109 Pagamento de Boleto | F38: 50207 | G38: 179.42
E39: CRIL EMPREENDIMENTO AMBIENTAL | G39: 0
B40: 45779 | C40: 0 | D40: 13105 | E40: 109 Pagamento de Boleto | F40: 50208 | G40: 389.3
E41: RV TECNOLOGIA S A | G41: 0
B42: 45779 | C42: 0 | D42: 13105 | E42: 109 Pagamento de Boleto | F42: 50209 | G42: 308.51
E43: POLIFARMA DISTRIBUIDORA DE MED | G43: 0
B44: 45779 | C44: 0 | D44: 13105 | E44: 109 Pagamento de Boleto | F44: 50210 | G44: 240.29
E45: POLIFARMA DISTRIBUIDORA DE MED | G45: 0
B46: 45779 | C46: 0 | D46: 13105 | E46: 109 Pagamento de Boleto | F46: 50211 | G46: 293.3
E47: POLIFARMA DISTRIBUIDORA DE MED | G47: 0
B48: 45779 | C48: 0 | D48: 13105 | E48: 109 Pagamento de Boleto | F48: 50212 | G48: 386.19
E49: POLIFARMA DISTRIBUIDORA DE MED | G49: 0
B50: 45779 | C50: 0 | D50: 13105 | E50: 109 Pagamento de Boleto | F50: 50213 | G50: 448.11
E51: POLIFARMA DISTRIBUIDORA DE MED | G51: 0
B52: 45779 | C52: 0 | D52: 13105 | E52: 109 Pagamento de Boleto | F52: 50214 | G52: 509.9
E53: DISTR DE MEDI SANTA CRUZ LTDA | G53: 0
B54: 45779 | C54: 0 | D54: 13105 | E54: 109 Pagamento de Boleto | F54: 50215 | G54: 48.28
E55: DISTR DE MEDI SANTA CRUZ LTDA | G55: 0
B56: 45779 | C56: 0 | D56: 13105 | E56: 109 Pagamento de Boleto | F56: 50216 | G56: 421.76
E57: DISTR DE MEDI SANTA CRUZ LTDA | G57: 0
B58: 45779 | C58: 0 | D58: 13105 | E58: 109 Pagamento de Boleto | F58: 50217 | G58: 233.32
E59: FARMAUM NATAL M LTDA | G59: 0
B60: 45779 | C60: 0 | D60: 13105 | E60: 109 Pagamento de Boleto | F60: 50218 | G60: 177.78
E61: FARMAUM NATAL M LTDA | G61: 0
B62: 45779 | C62: 0 | D62: 13105 | E62: 109 Pagamento de Boleto | F62: 50219 | G62: 241.03
E63: FARMAUM NATAL M LTDA | G63: 0
B64: 45779 | C64: 0 | D64: 13105 | E64: 109 Pagamento de Boleto | F64: 50220 | G64: 297.29
E65: FARMAUM NATAL M LTDA | G65: 0
B66: 45779 | C66: 0 | D66: 13105 | E66: 109 Pagamento de Boleto | F66: 50221 | G66: 230.71
E67: FARMAUM NATAL M LTDA | G67: 0
B68: 45779 | C68: 0 | D68: 13105 | E68: 109 Pagamento de Boleto | F68: 50222 | G68: 228.16
E69: FARMAUM NATAL M LTDA | G69: 0
B70: 45779 | C70: 0 | D70: 0 | E70: 351 BB Rende Fácil | F70: 9903 | G70: 2241.42
E71: Rende Facil | G71: 0
B72: 45782 | C72: 2035 | D72: 99015 | E72: 870 Transferência recebida | F72: 552035000900025 | G72: 1914.6 | H72: Instituto ISSERN
E73: 05/05 13:18 INSTITUTO ISSERN | G73: 0
B74: 45782 | C74: 2035 | D74: 99015 | E74: 870 Transferência recebida | F74: 552035000900025 | G74: 3315.32 | H74: Instituto ISSERN
E75: 05/05 13:18 INSTITUTO ISSERN | G75: 0
B76: 45782 | C76: 0 | D76: 14397 | E76: 821 Pix - Recebido | F76: 50939557258022 | G76: 379.37
E77: 05/05 09:39 00025469932400 MARCOS EFR | G77: 0
B78: 45782 | C78: 0 | D78: 14397 | E78: 821 Pix - Recebido | F78: 51032099162862 | G78: 675.04
E79: 05/05 10:32 08075247000189 UNNIQUE C L | G79: 0
B80: 45782 | C80: 0 | D80: 14397 | E80: 821 Pix - Recebido | F80: 51033429224292 | G80: 2523.9
E81: 05/05 10:33 08075247000189 UNNIQUE C L | G81: 0
B82: 45782 | C82: 0 | D82: 14397 | E82: 821 Pix - Recebido | F82: 464426405888901 | G82: 600
E83: 05/05 07:57 28155001000396 CLINICA SAN | G83: 0
B84: 45782 | C84: 0 | D84: 14397 | E84: 821 Pix - Recebido | F84: 464488850931391 | G84: 144.69
E85: 05/05 09:41 25469932400 MARCOS EFRAIM | G85: 0
B86: 45782 | C86: 0 | D86: 14397 | E86: 821 Pix - Recebido | F86: 464511109047351 | G86: 62.13
E87: 05/05 10:18 81315368404 FABIO DE OLIVE | G87: 0
B88: 45782 | C88: 1533 | D88: 99008 | E88: 234 Compra com Cartão | F88: 955941 | G88: 233.02
E89: 04/05 18:26 POSTO DINIZ - EMAUS | G89: 0
B90: 45782 | C90: 0 | D90: 13105 | E90: 375 Impostos | F90: 50501 | G90: 334.78
E91: RN TRIBUTACAO ICMS | G91: 0
B92: 45782 | C92: 0 | D92: 13105 | E92: 375 Impostos | F92: 50502 | G92: 183.69
E93: RN TRIBUTACAO ICMS | G93: 0
B94: 45782 | C94: 0 | D94: 13105 | E94: 375 Impostos | F94: 50503 | G94: 76.29
E95: RN TRIBUTACAO ICMS | G95: 0
B96: 45782 | C96: 0 | D96: 13105 | E96: 109 Pagamento de Boleto | F96: 50504 | G96: 434.25
E97: PROFARMA | G97: 0
B98: 45782 | C98: 0 | D98: 13105 | E98: 109 Pagamento de Boleto | F98: 50505 | G98: 544.39
E99: CIMED CO. S.A | G99: 0
B100: 45782 | C100: 0 | D100: 13105 | E100: 109 Pagamento de Boleto | F100: 50506 | G100: 393.9
...

Sheet Jun
A1: Status | B1: Dt. balancete | C1: Ag. origem | D1: Lote | E1: Histórico | F1: Documento | G1: Valor R$ | H1: Fatura | I1: Tipo | J1: Hematologia = | K1: =SUMIF(I7:I1066,"Hematologia", G7:G1097) -> 63636.03 | L1: Total = | M1: =SUBTOTAL(9,Jun!$G$2:$G$922) -> 954127.35
B2: 45807 | C2: 0 | D2: 0 | E2: 000 Saldo Anterior | G2: 0
B3: 45810 | C3: 0 | D3: 14175 | E3: 976 TED-Crédito em Conta | F3: 383054221 | G3: 5000
E4: 748 2207 03319496000159 MEDCAL FARMA H
B5: 45810 | C5: 0 | D5: 14397 | E5: 821 Pix - Recebido | F5: 21533353591952 | G5: 153.5
E6: 02/06 15:33 51058729000150 WELL LAB LA
A7: Baixado | B7: 45810 | C7: 0 | D7: 14138 | E7: 632 Ordem Bancária | F7: 202505300004586 | G7: 1415.81 | H7: 3711 | I7: Hematologia | J7: Coagulação = | K7: =SUMIF(I7:I1066,"Coagulação", G7:G1097) -> 3753.14 | L7: Baixados = | M7: =SUMIF(A:A,"Baixado",G:G) -> 117011.21
E8: ESTADO DO RIO GRANDE D
A9: Baixado | B9: 45810 | C9: 0 | D9: 14138 | E9: 632 Ordem Bancária | F9: 202505300004594 | G9: 1668.08 | H9: 3490 | I9: Hematologia | J9: TT/TTPA = | K9: =SUMIF(I7:I1066,"TT/TTPA", G7:G1097) -> 0 | L9: Pendente = | M9: =SUMIF(A:A,"Pendente",G:G) -> 18455.07
E10: ESTADO DO RIO GRANDE D
A11: Baixado | B11: 45810 | C11: 0 | D11: 14138 | E11: 632 Ordem Bancária | F11: 202505300004598 | G11: 3112.28 | H11: 3512 | I11: Hematologia | J11: Ionograma = | K11: =SUMIF(I7:I1066,"Ionograma", G7:G1097) -> 48389.2
E12: ESTADO DO RIO GRANDE D
A13: Baixado | B13: 45810 | C13: 0 | D13: 14138 | E13: 632 Ordem Bancária | F13: 202505300004607 | G13: 274.56 | H13: 3713 | I13: Coagulação
E14: ESTADO DO RIO GRANDE D
B15: 45810 | C15: 1533 | D15: 99008 | E15: 234 Compra com Cartão | F15: 421945 | G15: 189.28
E16: 02/06 16:11 TM COMBUSTIVEIS
B17: 45810 | C17: 0 | D17: 13105 | E17: 375 Impostos | F17: 60201 | G17: 259.55
E18: RN TRIBUTACAO ICMS
B19: 45810 | C19: 0 | D19: 13105 | E19: 109 Pagamento de Boleto | F19: 60202 | G19: 2587.92
E20: BANCO VOTORANTIM S/A
B21: 45810 | C21: 0 | D21: 13105 | E21: 109 Pagamento de Boleto | F21: 60203 | G21: 2677.12
E22: EBRAM PROD LABORATORIAIS LTDA
B23: 45810 | C23: 0 | D23: 13105 | E23: 109 Pagamento de Boleto | F23: 60204 | G23: 116.9
E24: CDH DIAGNOSTICA
B25: 45810 | C25: 0 | D25: 13105 | E25: 109 Pagamento de Boleto | F25: 60205 | G25: 1320
E26: Sanafarma Industria E Comercio
B27: 45810 | C27: 0 | D27: 13105 | E27: 109 Pagamento de Boleto | F27: 60206 | G27: 422.92
E28: POLIFARMA DISTRIBUIDORA DE MED
B29: 45810 | C29: 0 | D29: 13105 | E29: 109 Pagamento de Boleto | F29: 60207 | G29: 387.38
E30: POLIFARMA DISTRIBUIDORA DE MED
B31: 45810 | C31: 0 | D31: 13105 | E31: 109 Pagamento de Boleto | F31: 60208 | G31: 554.02
E32: DISTR DE MEDI SANTA CRUZ LTDA
B33: 45810 | C33: 0 | D33: 13105 | E33: 109 Pagamento de Boleto | F33: 60209 | G33: 344.74
E34: DISTR DE MEDI SANTA CRUZ LTDA
B35: 45810 | C35: 0 | D35: 13105 | E35: 109 Pagamento de Boleto | F35: 60210 | G35: 447.56
E36: RIOGRANDENSE DISTRIBUIDORA LTD
B37: 45810 | C37: 0 | D37: 13105 | E37: 109 Pagamento de Boleto | F37: 60211 | G37: 37.4
E38: RIOGRANDENSE D LTDA
B39: 45810 | C39: 0 | D39: 13105 | E39: 109 Pagamento de Boleto | F39: 60212 | G39: 240.44
E40: FARMAUM NATAL M LTDA
B41: 45810 | C41: 0 | D41: 13105 | E41: 109 Pagamento de Boleto | F41: 60213 | G41: 296.12
E42: DPC DISTRIBUIDOR ATACADISTA S
B43: 45810 | C43: 0 | D43: 13105 | E43: 109 Pagamento de Boleto | F43: 60214 | G43: 222.45
E44: G1 DISTRIBUIDORA DE PRODUTOS F
B45: 45810 | C45: 0 | D45: 13105 | E45: 109 Pagamento de Boleto | F45: 60215 | G45: 462.1
E46: RV TECNOLOGIA S A
B47: 45810 | C47: 0 | D47: 13105 | E47: 109 Pagamento de Boleto | F47: 60216 | G47: 49.9
E48: PJBANK PAGAMENTOS S A_1
B49: 45810 | C49: 0 | D49: 0 | E49: 351 BB Rende Fácil | F49: 9903 | G49: 1008.43
E50: Rende Facil
B51: 45811 | C51: 0 | D51: 14397 | E51: 821 Pix - Recebido | F51: 489521472727051 | G51: 684.43
E52: 03/06 09:02 48138959487 HUDMAR DE SOUS
B53: 45811 | C53: 0 | D53: 14397 | E53: 821 Pix - Recebido | F53: 489683252172211 | G53: 2000
E54: 03/06 13:32 03319496000159 Medcal Farm
B55: 45811 | C55: 0 | D55: 14397 | E55: 821 Pix - Recebido | F55: 489893449278021 | G55: 3000
E56: 03/06 19:22 13640653000187 SILVA & OLI
B57: 45811 | C57: 0 | D57: 13105 | E57: 109 Pagamento de Boleto | F57: 60301 | G57: 3290.33
E58: BANCO VOLKSWAGEN S.A.
B59: 45811 | C59: 0 | D59: 13105 | E59: 109 Pagamento de Boleto | F59: 60302 | G59: 341.16
E60: BACARIN RN INDUSTRIA E COMERCI
B61: 45811 | C61: 0 | D61: 13105 | E61: 109 Pagamento de Boleto | F61: 60303 | G61: 291.77
E62: POLIFARMA DISTRIBUIDORA DE MED
B63: 45811 | C63: 0 | D63: 13105 | E63: 109 Pagamento de Boleto | F63: 60304 | G63: 337.17
E64: POLIFARMA DISTRIBUIDORA DE MED
B65: 45811 | C65: 0 | D65: 13105 | E65: 109 Pagamento de Boleto | F65: 60305 | G65: 273.81
E66: DISTR DE MEDI SANTA CRUZ LTDA
B67: 45811 | C67: 0 | D67: 13105 | E67: 109 Pagamento de Boleto | F67: 60306 | G67: 393.9
E68: ANDRADE DISTRIBUIDORA LTDA
B69: 45811 | C69: 0 | D69: 13105 | E69: 109 Pagamento de Boleto | F69: 60307 | G69: 196.54
E70: FARMAUM NATAL M LTDA
B71: 45811 | C71: 0 | D71: 0 | E71: 351 BB Rende Fácil | F71: 9903 | G71: 559.75
E72: Rende Facil
B73: 45812 | C73: 0 | D73: 14175 | E73: 976 TED-Crédito em Conta | F73: 383351373 | G73: 3100
E74: 748 2207 03319496000159 MEDCAL FARMA H
B75: 45812 | C75: 0 | D75: 14397 | E75: 821 Pix - Recebido | F75: 41233072423332 | G75: 3096.05
E76: 04/06 12:33 09127333000150 ASSISTENCIA
B77: 45812 | C77: 0 | D77: 13105 | E77: 109 Pagamento de Boleto | F77: 60401 | G77: 1518
E78: OLIMPUS TECNOLOGIA EM SISTEMAS
B79: 45812 | C79: 0 | D79: 13105 | E79: 109 Pagamento de Boleto | F79: 60402 | G79: 1448.57
E80: WAMA PRODUTOS PARA LABORATORIO
B81: 45812 | C81: 0 | D81: 13105 | E81: 109 Pagamento de Boleto | F81: 60403 | G81: 836.73
E82: DISTR DE MEDI SANTA CRUZ LTDA
B83: 45812 | C83: 0 | D83: 13105 | E83: 109 Pagamento de Boleto | F83: 60404 | G83: 337.78
E84: DISTR DE MEDI SANTA CRUZ LTDA
B85: 45812 | C85: 0 | D85: 13105 | E85: 109 Pagamento de Boleto | F85: 60405 | G85: 70.91
E86: DISTR DE MEDI SANTA CRUZ LTDA
B87: 45812 | C87: 0 | D87: 13105 | E87: 109 Pagamento de Boleto | F87: 60406 | G87: 375.82
E88: POLIFARMA DISTRIBUIDORA DE MED
B89: 45812 | C89: 0 | D89: 13105 | E89: 109 Pagamento de Boleto | F89: 60407 | G89: 468.19
E90: POLIFARMA DISTRIBUIDORA DE MED
B91: 45812 | C91: 0 | D91: 13105 | E91: 109 Pagamento de Boleto | F91: 60408 | G91: 469.68
E92: STER BOM IND E COM LTDA
B93: 45812 | C93: 0 | D93: 13105 | E93: 109 Pagamento de Boleto | F93: 60409 | G93: 287.72
E94: FARMAUM NATAL M LTDA
B95: 45812 | C95: 0 | D95: 13105 | E95: 109 Pagamento de Boleto | F95: 60410 | G95: 279.44
E96: FARMAUM NATAL M LTDA
B97: 45812 | C97: 0 | D97: 0 | E97: 351 BB Rende Fácil | F97: 9903 | G97: 103.21
E98: Rende Facil
B99: 45813 | C99: 0 | D99: 14175 | E99: 976 TED-Crédito em Conta | F99: 34599346 | G99: 11424
E100: 104 0760 12148443000103 FMS DE RIACHUE
...

Sheet Jul
A1: Status | B1: Dt. balancete | C1: Ag. origem | D1: Lote | E1: Histórico | F1: Documento | G1: Valor R$ | H1: Fatura | I1: Tipo | J1: Hematologia/165 = | K1: =SUMIF(I7:I1064,"Hematologia", G7:G1095) -> 123313.73 | L1: Total = | M1: =SUBTOTAL(9,Jul!$G$2:$G$1080) -> 1237754.4
B2: 45839 | C2: 0 | D2: 14175 | E2: 976 TED-Pag Fornecedores | F2: 35224465 | G2: 26626.61
E3: 104 1101 11802520000134 FUNDO MUNICIPA | G3: 0
B4: 45839 | C4: 0 | D4: 14175 | E4: 976 TED-Pag Fornecedores | F4: 35224508 | G4: 23761.4
E5: 104 1101 11802520000134 FUNDO MUNICIPA | G5: 0
A6: Baixado | B6: 45839 | C6: 0 | D6: 14138 | E6: 632 Ordem Bancária | F6: 202506300112173 | G6: 875.17 | H6: FT 3538 | I6: Coagulação | J6: Coagulação/141 = | K6: =SUMIF(I6:I1063,"Coagulação", G6:G1094) -> 5655.44 | L6: Baixados = | M6: =SUMIF(A:A,"Baixado",G:G) -> 239520.58
E7: ESTADO DO RIO GRANDE D | G7: 0
A8: Baixado | B8: 45839 | C8: 0 | D8: 14138 | E8: 632 Ordem Bancária | F8: 202506300132322 | G8: 3030.31 | H8: FTs 3094 e 3115 | I8: Ionograma | J8: TT/TTPA = | K8: =SUMIF(I6:I1063,"TT/TTPA", G6:G1094) -> 0 | L8: Pendente = | M8: =SUMIF(A:A,"Pendente",G:G) -> 10612.82
E9: ESTADO DO RIO GRANDE D | G9: 0
A10: Baixado | B10: 45839 | C10: 0 | D10: 14138 | E10: 632 Ordem Bancária | F10: 202506300132335 | G10: 1476.65 | H10: FT 3629 | I10: Ionograma | J10: Ionograma/220 = | K10: =SUMIF(I6:I1063,"Ionograma", G6:G1094) -> 109946.14
E11: ESTADO DO RIO GRANDE D | G11: 0
A12: Baixado | B12: 45839 | C12: 0 | D12: 14138 | E12: 632 Ordem Bancária | F12: 202506300132337 | G12: 1612.42 | H12: FT 2923 | I12: Ionograma
E13: ESTADO DO RIO GRANDE D | G13: 0
A14: Baixado | B14: 45839 | C14: 0 | D14: 14138 | E14: 632 Ordem Bancária | F14: 202506300132339 | G14: 1553.66 | H14: FT 3675 | I14: Ionograma
E15: ESTADO DO RIO GRANDE D | G15: 0
A16: Baixado | B16: 45839 | C16: 0 | D16: 14138 | E16: 632 Ordem Bancária | F16: 202506300132346 | G16: 1476.65 | H16: FT 3671 | I16: Ionograma
E17: ESTADO DO RIO GRANDE D | G17: 0
A18: Baixado | B18: 45839 | C18: 0 | D18: 14138 | E18: 632 Ordem Bancária | F18: 202506300132347 | G18: 589.59 | H18: FTs 3715 | I18: Coagulação
E19: ESTADO DO RIO GRANDE D | G19: 0
A20: Baixado | B20: 45839 | C20: 0 | D20: 14138 | E20: 632 Ordem Bancária | F20: 202506300132351 | G20: 17518.9 | H20: FTs 2445.1, 2447.1, 2915.1, 2921.1, 2926 | I20: Ionograma | J20: R$ 15691,68 - No extrato não coube todas as faturas.
E21: ESTADO DO RIO GRANDE D | G21: 0
A22: Baixado | B22: 45839 | C22: 0 | D22: 14138 | E22: 632 Ordem Bancária | F22: 202506300132352 | G22: 6164.33 | H22: FTs 3707 | I22: Hematologia
E23: ESTADO DO RIO GRANDE D | G23: 0
A24: Baixado | B24: 45839 | C24: 0 | D24: 14138 | E24: 632 Ordem Bancária | F24: 202506300132354 | G24: 1553.66 | H24: FT 3696 | I24: Ionograma
E25: ESTADO DO RIO GRANDE D | G25: 0
A26: Baixado | B26: 45839 | C26: 0 | D26: 14138 | E26: 632 Ordem Bancária | F26: 202506300132359 | G26: 1476.65 | H26: FT 3685 | I26: Ionograma
E27: ESTADO DO RIO GRANDE D | G27: 0
A28: Baixado | B28: 45839 | C28: 0 | D28: 14138 | E28: 632 Ordem Bancária | F28: 202506300132363 | G28: 1476.65 | H28: FT 2753 | I28: Ionograma
E29: ESTADO DO RIO GRANDE D | G29: 0
A30: Baixado | B30: 45839 | C30: 0 | D30: 14138 | E30: 632 Ordem Bancária | F30: 202506300132365 | G30: 1553.66 | H30: FT 3605 | I30: Ionograma
E31: ESTADO DO RIO GRANDE D | G31: 0
A32: Baixado | B32: 45839 | C32: 0 | D32: 14138 | E32: 632 Ordem Bancária | F32: 202506300132367 | G32: 1476.65 | H32: FT 3594 | I32: Ionograma
E33: ESTADO DO RIO GRANDE D | G33: 0
A34: Baixado | B34: 45839 | C34: 0 | D34: 14138 | E34: 632 Ordem Bancária | F34: 202506300132369 | G34: 1476.65 | H34: FT 2335 | I34: Ionograma
E35: ESTADO DO RIO GRANDE D | G35: 0
A36: Baixado | B36: 45839 | C36: 0 | D36: 14138 | E36: 632 Ordem Bancária | F36: 202506300132371 | G36: 3237.94 | H36: FATURA 3524 | I36: Hematologia
E37: ESTADO DO RIO GRANDE D | G37: 0
A38: Baixado | B38: 45839 | C38: 0 | D38: 14138 | E38: 632 Ordem Bancária | F38: 202506300132372 | G38: 1668.08 | H38: FATURA 3481 | I38: Hematologia
E39: ESTADO DO RIO GRANDE D | G39: 0
B40: 45839 | C40: 1533 | D40: 99015 | E40: 470 Transferência enviada | F40: 551845000113366 | G40: 3605.31
E41: 01/07 15:57 JONATAN EDUARDO M SILVA | G41: 0
B42: 45839 | C42: 1533 | D42: 99015 | E42: 470 Transferência enviada | F42: 552035000108588 | G42: 3687.48
E43: 01/07 15:55 RHOZA MARIA ARAUJO DE ME | G43: 0
B44: 45839 | C44: 1533 | D44: 99015 | E44: 470 Transferência enviada | F44: 552878000021801 | G44: 20000
E45: 01/07 10:41 MAGNUS SOARES DA COSTA | G45: 0
B46: 45839 | C46: 1533 | D46: 99015 | E46: 470 Transferência enviada | F46: 552878000021801 | G46: 9660.71
E47: 01/07 15:02 MAGNUS SOARES DA COSTA | G47: 0
B48: 45839 | C48: 0 | D48: 13105 | E48: 144 Pix - Enviado | F48: 70101 | G48: 15000
E49: 01/07 10:42 PAULO SERGIO SOARES DA COS | G49: 0
B50: 45839 | C50: 0 | D50: 13105 | E50: 109 Pagamento de Boleto | F50: 70102 | G50: 149.98
E51: RV TECNOLOGIA S A | G51: 0
B52: 45839 | C52: 0 | D52: 13105 | E52: 375 Impostos | F52: 70103 | G52: 111.8
E53: RN TRIBUTACAO ICMS | G53: 0
B54: 45839 | C54: 0 | D54: 13105 | E54: 375 Impostos | F54: 70104 | G54: 492.46
E55: RN TRIBUTACAO ICMS | G55: 0
B56: 45839 | C56: 0 | D56: 13105 | E56: 109 Pagamento de Boleto | F56: 70105 | G56: 327.23
E57: DISTRIBUIDORA SERIDO | G57: 0
B58: 45839 | C58: 0 | D58: 13105 | E58: 109 Pagamento de Boleto | F58: 70106 | G58: 1117.53
E59: LABOR IMPORT COMERCIAL IMPORTA | G59: 0
B60: 45839 | C60: 0 | D60: 13105 | E60: 109 Pagamento de Boleto | F60: 70107 | G60: 626.49
E61: DISTR DE MEDI SANTA CRUZ LTDA | G61: 0
B62: 45839 | C62: 0 | D62: 13105 | E62: 109 Pagamento de Boleto | F62: 70108 | G62: 266.12
E63: ANDRADE DISTRIBUIDORA LTDA | G63: 0
B64: 45839 | C64: 0 | D64: 13105 | E64: 144 Pix - Enviado | F64: 70109 | G64: 10000
E65: 01/07 11:29 M & S LOCACOES LTDA | G65: 0
B66: 45839 | C66: 0 | D66: 13105 | E66: 109 Pagamento de Boleto | F66: 70110 | G66: 5118.2
E67: APPARAT BRASIL COMERCIO DE REA | G67: 0
B68: 45839 | C68: 0 | D68: 13105 | E68: 109 Pagamento de Boleto | F68: 70111 | G68: 5069.3
E69: APPARAT BRASIL COMERCIO DE REA | G69: 0
B70: 45839 | C70: 0 | D70: 13105 | E70: 109 Pagamento de Boleto | F70: 70112 | G70: 2026.96
E71: APPARAT BRASIL COMERCIO DE REA | G71: 0
B72: 45839 | C72: 0 | D72: 13105 | E72: 109 Pagamento de Boleto | F72: 70113 | G72: 8761.11
E73: APPARAT BRASIL COMERCIO DE REA | G73: 0
B74: 45839 | C74: 0 | D74: 13105 | E74: 109 Pagamento de Boleto | F74: 70114 | G74: 6606.81
E75: APPARAT BRASIL COMERCIO DE REA | G75: 0
B76: 45839 | C76: 0 | D76: 13105 | E76: 144 Pix - Enviado | F76: 70115 | G76: 6005.16
E77: 01/07 17:34 PAULO SERGIO SOARES DA COS | G77: 0
B78: 45839 | C78: 0 | D78: 0 | E78: 798 BB Rende Fácil | F78: 9903 | G78: 27.02
E79: Rende Facil | G79: 0
B80: 45840 | C80: 0 | D80: 14397 | E80: 821 Pix - Recebido | F80: 21129211427881 | G80: 13503.68
E81: 02/07 11:29 32958432000104 SLE SERVICO | G81: 0
B82: 45840 | C82: 0 | D82: 14397 | E82: 821 Pix - Recebido | F82: 21516512740112 | G82: 163.64
E83: 02/07 15:16 00061690104449 ELIANE PORT | G83: 0
B84: 45840 | C84: 0 | D84: 14397 | E84: 821 Pix - Recebido | F84: 21557052280201 | G84: 91.54
E85: 02/07 15:57 35293141000124 Centro De A | G85: 0
A86: Baixado | B86: 45840 | C86: 0 | D86: 14138 | E86: 632 Ordem Bancária | F86: 202507010020205 | G86: 1612.42 | H86: FT 3030 | I86: Ionograma
E87: ESTADO DO RIO GRANDE D | G87: 0
A88: Baixado | B88: 45840 | C88: 0 | D88: 14138 | E88: 632 Ordem Bancária | F88: 202507010020206 | G88: 1476.65 | H88: FT 2988 | I88: Ionograma
E89: ESTADO DO RIO GRANDE D | G89: 0
A90: Baixado | B90: 45840 | C90: 0 | D90: 14138 | E90: 632 Ordem Bancária | F90: 202507010032241 | G90: 759.93 | H90: FATURA 3726 | I90: Coagulação
E91: ESTADO DO RIO GRANDE D | G91: 0
A92: Baixado | B92: 45840 | C92: 0 | D92: 14138 | E92: 632 Ordem Bancária | F92: 202507010032246 | G92: 34.92 | H92: FT 3542 | I92: Coagulação
E93: ESTADO DO RIO GRANDE D | G93: 0
A94: Baixado | B94: 45840 | C94: 0 | D94: 14138 | E94: 632 Ordem Bancária | F94: 202507010032256 | G94: 1553.66 | H94: FATURA 3651 | I94: Ionograma
E95: ESTADO DO RIO GRANDE D | G95: 0
A96: Baixado | B96: 45840 | C96: 0 | D96: 14138 | E96: 632 Ordem Bancária | F96: 202507010032258 | G96: 1476.65 | H96: FATURA 3633 | I96: Ionograma
E97: ESTADO DO RIO GRANDE D | G97: 0
A98: Baixado | B98: 45840 | C98: 0 | D98: 14138 | E98: 632 Ordem Bancária | F98: 202507010032260 | G98: 1553.66 | H98: FATURA 3677 | I98: Ionograma | J98: Pagamento informado duas vezes - pagamento correto
E99: ESTADO DO RIO GRANDE D | G99: 0
A100: Baixado | B100: 45840 | C100: 0 | D100: 14138 | E100: 632 Ordem Bancária | F100: 202507010032261 | G100: 2305.38 | H100: FTs 2179.1 e 2192 | I100: Ionograma
...

Sheet Ago
A1: Status | B1: Dt. balancete | C1: Ag. origem | D1: Lote | E1: Histórico | F1: Documento | G1: Valor R$ | H1: Fatura | I1: Tipo | J1: Hematologia/165 = | K1: =SUMIF(I:I,"Hematologia", G:G) -> 72031.1 | L1: Total = | M1: =SUBTOTAL(9,Ago!$G$2:$G$1026) -> 1072735.4
B2: 45869 | C2: 0 | D2: 0 | E2: 000 Saldo Anterior | G2: 0
B3: 45870 | C3: 0 | D3: 14397 | E3: 821 Pix - Recebido | F3: 11032315887311 | G3: 4409
E4: 01/08 10:32 51936203000125 Cliniclab E | G4: 0
B5: 45870 | C5: 0 | D5: 14397 | E5: 821 Pix - Recebido | F5: 11347282025861 | G5: 5000
E6: 01/08 13:47 83738657487 MAGNUS SOARES | G6: 0
A7: Baixado | B7: 45870 | C7: 0 | D7: 14138 | E7: 632 Ordem Bancária | F7: 202507310001855 | G7: 1241.98 | H7: Fatura 3889 | I7: Hematologia | J7: Coagulação/141 = | K7: =SUMIF(I:I,"Coagulação", G:G) -> 9345.69 | L7: Baixados = | M7: =SUMIF(A:A,"Baixado",G:G) -> 171794.18
E8: ESTADO DO RIO GRANDE D | G8: 0
A9: Baixado | B9: 45870 | C9: 0 | D9: 14138 | E9: 632 Ordem Bancária | F9: 202507310001857 | G9: 1232.84 | H9: Fatura 3849 | I9: Hematologia | J9: Ionograma/220 = | K9: =SUMIF(I:I,"Ionograma", G:G) -> 40910.9 | L9: Pendente = | M9: =SUMIF(A:A,"Pendente",G:G) -> 5474.25
E10: ESTADO DO RIO GRANDE D | G10: 0
A11: Baixado | B11: 45870 | C11: 0 | D11: 14138 | E11: 632 Ordem Bancária | F11: 202507310001859 | G11: 4167.09 | H11: Fatura 3897 e 3848 | I11: Hematologia
E12: ESTADO DO RIO GRANDE D | G12: 0
A13: Baixado | B13: 45870 | C13: 0 | D13: 14138 | E13: 632 Ordem Bancária | F13: 202507310001861 | G13: 2439.98 | H13: Fatura 3914 | I13: Hematologia
E14: ESTADO DO RIO GRANDE D | G14: 0
A15: Baixado | B15: 45870 | C15: 0 | D15: 14138 | E15: 632 Ordem Bancária | F15: 202507310001865 | G15: 1668.08 | H15: FATURA 3836 | I15: Hematologia
E16: ESTADO DO RIO GRANDE D | G16: 0
A17: Baixado | B17: 45870 | C17: 0 | D17: 14138 | E17: 632 Ordem Bancária | F17: 202507310001868 | G17: 1063.96 | H17: FATURA 3903 | I17: Hematologia
E18: ESTADO DO RIO GRANDE D | G18: 0
A19: Baixado | B19: 45870 | C19: 0 | D19: 14138 | E19: 632 Ordem Bancária | F19: 202507310001871 | G19: 1668.08 | H19: FATURA 3840 | I19: Hematologia
E20: ESTADO DO RIO GRANDE D | G20: 0
B21: 45870 | C21: 1533 | D21: 99015 | E21: 470 Transferência enviada | F21: 551845000113366 | G21: 3605.31
E22: 01/08 15:37 JONATAN EDUARDO M SILVA | G22: 0
B23: 45870 | C23: 1533 | D23: 99015 | E23: 470 Transferência enviada | F23: 552035000108588 | G23: 3687.48
E24: 01/08 15:28 RHOZA MARIA ARAUJO DE ME | G24: 0
B25: 45870 | C25: 0 | D25: 13105 | E25: 144 Pix - Enviado | F25: 80101 | G25: 154.88
E26: 01/08 08:42 Posto Qualy Boa Esperanca | G26: 0
B27: 45870 | C27: 0 | D27: 13105 | E27: 109 Pagamento de Boleto | F27: 80102 | G27: 378.65
E28: DISTR DE MEDI SANTA CRUZ LTDA | G28: 0
B29: 45870 | C29: 0 | D29: 13105 | E29: 109 Pagamento de Boleto | F29: 80103 | G29: 302.35
E30: RV TECNOLOGIA S A | G30: 0
B31: 45870 | C31: 0 | D31: 13105 | E31: 109 Pagamento de Boleto | F31: 80104 | G31: 677.93
E32: POLIFARMA DISTRIBUIDORA DE MED | G32: 0
B33: 45870 | C33: 0 | D33: 13105 | E33: 109 Pagamento de Boleto | F33: 80105 | G33: 555.51
E34: POLIFARMA DISTRIBUIDORA DE MED | G34: 0
B35: 45870 | C35: 0 | D35: 13105 | E35: 109 Pagamento de Boleto | F35: 80106 | G35: 459.42
E36: POLIFARMA DISTRIBUIDORA DE MED | G36: 0
B37: 45870 | C37: 0 | D37: 13105 | E37: 109 Pagamento de Boleto | F37: 80107 | G37: 190.37
E38: PROFARMA DISTRIBUIDORA DE PROD | G38: 0
B39: 45870 | C39: 0 | D39: 13105 | E39: 144 Pix - Enviado | F39: 80108 | G39: 16000
E40: 01/08 14:34 M & S LOCACOES LTDA | G40: 0
B41: 45870 | C41: 0 | D41: 0 | E41: 798 BB Rende Fácil | F41: 9903 | G41: 3120.89
E42: Rende Facil | G42: 0
B43: 45873 | C43: 3525 | D43: 99021 | E43: 870 Transferência recebida | F43: 613525000032047 | G43: 327.13
E44: 04/08 14:55 D&M LABORATORIO DE ANALI | G44: 0
B45: 45873 | C45: 0 | D45: 14175 | E45: 976 TED-Crédito em Conta | F45: 389865021 | G45: 3000
E46: 748 2207 03319496000159 MEDCAL FARMA H | G46: 0
B47: 45873 | C47: 0 | D47: 14397 | E47: 821 Pix - Recebido | F47: 40837539959932 | G47: 275.11
E48: 04/08 08:37 03423259000133 LABVIDA LTD | G48: 0
B49: 45873 | C49: 0 | D49: 14397 | E49: 821 Pix - Recebido | F49: 41821482724062 | G49: 3000
E50: 04/08 18:21 13640653000187 SILVA OLI | G50: 0
A51: Baixado | B51: 45873 | C51: 0 | D51: 14138 | E51: 632 Ordem Bancária | F51: 202508010020258 | G51: 171.36 | H51: PP da loca o de equipamento de ionogram FAT 3290 | I51: Maria Alice
E52: ESTADO DO RIO GRANDE D | G52: 0
A53: Baixado | B53: 45873 | C53: 0 | D53: 14138 | E53: 632 Ordem Bancária | F53: 202508010034055 | G53: 9346.16 | H53: FT 3801.1 e 3751.1 | I53: Hematologia
E54: ESTADO DO RIO GRANDE D | G54: 0
A55: Baixado | B55: 45873 | C55: 0 | D55: 14138 | E55: 632 Ordem Bancária | F55: 202508010034057 | G55: 3832.93 | H55: Fts 3901, 3896, 3847 e 3834 | I55: Hematologia
E56: ESTADO DO RIO GRANDE D | G56: 0
B57: 45873 | C57: 1533 | D57: 99008 | E57: 234 Compra com Cartão | F57: 13227 | G57: 35
E58: 04/08 19:42 QUIOSQUE DO ABENCOAD | G58: 0
B59: 45873 | C59: 1533 | D59: 99008 | E59: 234 Compra com Cartão | F59: 44205 | G59: 100
E60: 02/08 21:16 ZP*POSTO JOAO CAMARA | G60: 0
B61: 45873 | C61: 1533 | D61: 99008 | E61: 234 Compra com Cartão | F61: 84179 | G61: 110
E62: 04/08 20:45 FranciscoGilberto | G62: 0
B63: 45873 | C63: 1533 | D63: 99008 | E63: 234 Compra com Cartão | F63: 108431 | G63: 212.02
E64: 02/08 22:08 CM COMERCIAL DE COMB | G64: 0
B65: 45873 | C65: 1533 | D65: 99008 | E65: 234 Compra com Cartão | F65: 730869 | G65: 230
E66: 04/08 17:26 R C F SILVA | G66: 0
B67: 45873 | C67: 0 | D67: 13105 | E67: 375 Impostos | F67: 80401 | G67: 122.62
E68: RN TRIBUTACAO ICMS | G68: 0
B69: 45873 | C69: 0 | D69: 13105 | E69: 375 Impostos | F69: 80402 | G69: 2717.43
E70: RN TRIBUTACAO ICMS | G70: 0
B71: 45873 | C71: 0 | D71: 13105 | E71: 109 Pagamento de Boleto | F71: 80403 | G71: 7437.3
E72: APPARAT BRASIL COMERCIO DE REA | G72: 0
B73: 45873 | C73: 0 | D73: 13105 | E73: 109 Pagamento de Boleto | F73: 80404 | G73: 420
E74: Microline Comercio E Servicos | G74: 0
B75: 45873 | C75: 0 | D75: 13105 | E75: 109 Pagamento de Boleto | F75: 80405 | G75: 1320
E76: Sanafarma | G76: 0
B77: 45873 | C77: 0 | D77: 13105 | E77: 109 Pagamento de Boleto | F77: 80406 | G77: 1518
E78: OLIMPUS TECNOLOGIA EM SISTEMAS | G78: 0
B79: 45873 | C79: 0 | D79: 13105 | E79: 109 Pagamento de Boleto | F79: 80407 | G79: 1550
E80: CONFIANCA FUNDO DE INVEST EM D | G80: 0
B81: 45873 | C81: 0 | D81: 13105 | E81: 109 Pagamento de Boleto | F81: 80408 | G81: 724.51
E82: DISTR DE MEDI SANTA CRUZ LTDA | G82: 0
B83: 45873 | C83: 0 | D83: 13105 | E83: 109 Pagamento de Boleto | F83: 80409 | G83: 225.29
E84: FARMAUM NATAL M LTDA | G84: 0
B85: 45873 | C85: 0 | D85: 13105 | E85: 109 Pagamento de Boleto | F85: 80410 | G85: 300.77
E86: RIO GRANDENSE DISTRIBUIDORA LT | G86: 0
B87: 45873 | C87: 0 | D87: 13105 | E87: 375 Impostos | F87: 80411 | G87: 160.84
E88: RN TRIBUTACAO ICMS | G88: 0
B89: 45873 | C89: 0 | D89: 0 | E89: 351 BB Rende Fácil | F89: 9903 | G89: 2768.91
E90: Rende Facil | G90: 0
B91: 45874 | C91: 0 | D91: 14397 | E91: 821 Pix - Recebido | F91: 51637053768252 | G91: 81.38
E92: 05/08 16:37 40807109000150 L A E S LAB | G92: 0
A93: Baixado | B93: 45874 | C93: 0 | D93: 14138 | E93: 632 Ordem Bancária | F93: 202508040050720 | G93: 1476.65 | H93: FTs 3769.1 | I93: Ionograma
E94: ESTADO DO RIO GRANDE D | G94: 0
A95: Baixado | B95: 45874 | C95: 0 | D95: 14138 | E95: 632 Ordem Bancária | F95: 202508040050721 | G95: 1165.25 | H95: FT 3780 | I95: Ionograma
E96: ESTADO DO RIO GRANDE D | G96: 0
A97: Baixado | B97: 45874 | C97: 0 | D97: 14138 | E97: 632 Ordem Bancária | F97: 202508040050726 | G97: 1476.65 | H97: FT 3864.1 | I97: Ionograma
E98: ESTADO DO RIO GRANDE D | G98: 0
A99: Baixado | B99: 45874 | C99: 0 | D99: 14138 | E99: 632 Ordem Bancária | F99: 202508040050727 | G99: 1165.25 | H99: FT 3875.1 | I99: Ionograma
E100: ESTADO DO RIO GRANDE D | G100: 0
...

Sheet Set
J1: Hematologia/165 = | K1: =SUMIF(I:I,"Hematologia",G:G) -> 28935.3 | L1: Total = | M1: =SUM(G51:G723) -> 580645.5
J2: Coagulação/141 = | K2: =SUMIF(I:I,"Coagulação",G:G) -> 9797.35 | L2: Baixados = | M2: =SUMIF(A:A,"Baixado",G:G) -> 69516.62
J3: Ionograma/220 = | K3: =SUMIF(I:I,"Ionograma",G:G) -> 31469.53 | L3: Pendente = | M3: =SUMIF(A:A,"Pendente",G:G) -> 22728.27
A4: Status | B4: Dt. balancete | C4: Ag. origem | D4: Lote | E4: Histórico | F4: Documento | G4: Valor R$ | H4: Fatura | I4: Tipo
B5: 45901 | C5: 0 | D5: 14175 | E5: 976 TED-Pag Fornecedores | F5: 35353866 | G5: 6542.84
E6: 104 7853 10709689000181 FUNDO DE SAUDE
B7: 45901 | C7: 0 | D7: 14175 | E7: 976 TED-Crédito em Conta | F7: 35374770 | G7: 4500
E8: 748 2207 03319496000159 MEDCAL FARMA H
B9: 45901 | C9: 0 | D9: 14397 | E9: 821 Pix - Recebido | F9: 11605065598831 | G9: 1651.9
E10: 01/09 16:05 48138959487 HUDMAR DE SOUS
B11: 45901 | C11: 1533 | D11: 99008 | E11: 234 Compra com Cartão | F11: 231865 | G11: 119.66
E12: 01/09 21:04 POSTO QUALY
B13: 45901 | C13: 0 | D13: 13105 | E13: 109 Pagamento de Boleto | F13: 90101 | G13: 2361.61
E14: EBRAM PROD LABORATORIAIS LTDA
B15: 45901 | C15: 0 | D15: 13105 | E15: 375 Impostos | F15: 90102 | G15: 620.26
E16: RN TRIBUTACAO ICMS
B17: 45901 | C17: 0 | D17: 13105 | E17: 375 Impostos | F17: 90103 | G17: 644.51
E18: RN TRIBUTACAO ICMS
B19: 45901 | C19: 0 | D19: 13105 | E19: 109 Pagamento de Boleto | F19: 90104 | G19: 244.05
E20: RV TECNOLOGIA S A
B21: 45901 | C21: 0 | D21: 13105 | E21: 109 Pagamento de Boleto | F21: 90105 | G21: 1192.58
E22: DISTR DE MEDI SANTA CRUZ LTDA
B23: 45901 | C23: 0 | D23: 13105 | E23: 109 Pagamento de Boleto | F23: 90106 | G23: 286.17
E24: POLIFARMA DISTRIBUIDORA DE MED
B25: 45901 | C25: 0 | D25: 13105 | E25: 109 Pagamento de Boleto | F25: 90107 | G25: 265.34
E26: FARMAUM NATAL M LTDA
B27: 45901 | C27: 0 | D27: 13105 | E27: 109 Pagamento de Boleto | F27: 90108 | G27: 191.44
E28: FARMAUM NATAL M LTDA
B29: 45901 | C29: 0 | D29: 13105 | E29: 109 Pagamento de Boleto | F29: 90109 | G29: 446.22
E30: ANDRADE DISTRIBUIDORA LTDA
B31: 45901 | C31: 0 | D31: 13105 | E31: 375 Impostos | F31: 90110 | G31: 353.36
E32: RN TRIBUTACAO ICMS
B33: 45901 | C33: 0 | D33: 13105 | E33: 375 Impostos | F33: 90111 | G33: 246.71
E34: RN TRIBUTACAO ICMS
B35: 45901 | C35: 0 | D35: 13105 | E35: 109 Pagamento de Boleto | F35: 90112 | G35: 176.43
E36: DISTR DE MEDI SANTA CRUZ LTDA
B37: 45901 | C37: 0 | D37: 13105 | E37: 109 Pagamento de Boleto | F37: 90113 | G37: 446.78
E38: POLIFARMA DISTRIBUIDORA DE MED
B39: 45901 | C39: 0 | D39: 13105 | E39: 109 Pagamento de Boleto | F39: 90114 | G39: 233.5
E40: DISTRIBUIDORA SERIDO
B41: 45901 | C41: 0 | D41: 13105 | E41: 109 Pagamento de Boleto | F41: 90115 | G41: 339.81
E42: PROFARMA DISTRIBUIDORA DE PROD
B43: 45901 | C43: 0 | D43: 13105 | E43: 109 Pagamento de Boleto | F43: 90116 | G43: 287.81
E44: RIOGRANDENSE DISTRIBUIDORA LTD
B45: 45901 | C45: 0 | D45: 13105 | E45: 144 Pix - Enviado | F45: 90117 | G45: 3300
E46: 01/09 14:43 M & S LOCACOES LTDA
B47: 45901 | C47: 0 | D47: 0 | E47: 351 BB Rende Fácil | F47: 9903 | G47: 938.5
E48: Rende Facil
B49: 45902 | C49: 1845 | D49: 99021 | E49: 870 Transferência recebida | F49: 611845000040070 | G49: 873.41
E50: 02/09 10:36 RP SERVICOS LABORATORIAI
A51: Pendente | B51: 45902 | C51: 0 | D51: 14056 | E51: 632 Ordem Banc 12 Sec Tes Nac | F51: 4322692000000 | G51: 9679.6 | H51: APL NUHANT - NF 00003985.1 DE 06 08 2025 UG. 120616 NUHANT PROCESSO 67222003374202186 CONTRATO 018 BANT-HARF 2021 | I51: Base Áerea
E52: 003944290185-81 BASE AEREA DE NATAL
B53: 45902 | C53: 0 | D53: 14397 | E53: 821 Pix - Recebido | F53: 21154537158382 | G53: 3000
E54: 02/09 11:54 13640653000187 SILVA OLI
B55: 45902 | C55: 0 | D55: 14397 | E55: 821 Pix - Recebido | F55: 21845372093182 | G55: 1209.86
E56: 02/09 18:45 20585406000190 DRA ANINHA
B57: 45902 | C57: 1533 | D57: 99008 | E57: 234 Compra com Cartão | F57: 83988 | G57: 95
E58: 02/09 14:32 POSTO ESTRELA DA BR
B59: 45902 | C59: 0 | D59: 13105 | E59: 109 Pagamento de Boleto | F59: 90201 | G59: 7437.3
E60: APPARAT BRASIL COMERCIO DE REA
B61: 45902 | C61: 0 | D61: 13105 | E61: 109 Pagamento de Boleto | F61: 90202 | G61: 1431.98
E62: TROCA TRANSPORTES LTDA
B63: 45902 | C63: 0 | D63: 0 | E63: 351 BB Rende Fácil | F63: 9903 | G63: 5798.59
E64: Rende Facil
B65: 45903 | C65: 0 | D65: 14397 | E65: 821 Pix - Recebido | F65: 30956134067142 | G65: 641.68
E66: 03/09 09:56 38095897000157 CLINCORDIS
B67: 45903 | C67: 0 | D67: 14397 | E67: 821 Pix - Recebido | F67: 31516518956742 | G67: 119.94
E68: 03/09 15:16 00081315368404 FABIO OLIVE
A69: Baixado | B69: 45903 | C69: 0 | D69: 14138 | E69: 632 Ordem Bancária | F69: 202509020000014 | G69: 2979.18 | H69: NF 2635 e 2673 - | I69: Hematologia
E70: ESTADO DO RIO GRANDE D
A71: Baixado | B71: 45903 | C71: 0 | D71: 14138 | E71: 632 Ordem Bancária | F71: 202509020022140 | G71: 412.6 | H71: FT 4015.1 | I71: Hematologia
E72: ESTADO DO RIO GRANDE D
A73: Baixado | B73: 45903 | C73: 0 | D73: 14138 | E73: 632 Ordem Bancária | F73: 202509020022141 | G73: 1668.08 | H73: FT 3935.1 | I73: Hematologia
E74: ESTADO DO RIO GRANDE D
A75: Baixado | B75: 45903 | C75: 0 | D75: 14138 | E75: 632 Ordem Bancária | F75: 202509020022161 | G75: 1668.08 | H75: FT 3930.1 | I75: Hematologia
E76: ESTADO DO RIO GRANDE D
A77: Baixado | B77: 45903 | C77: 0 | D77: 14138 | E77: 632 Ordem Bancária | F77: 202509020022162 | G77: 2201.21 | H77: FT 3991.1 | I77: Hematologia
E78: ESTADO DO RIO GRANDE D
A79: Baixado | B79: 45903 | C79: 0 | D79: 14138 | E79: 632 Ordem Bancária | F79: 202509020022171 | G79: 1668.08 | H79: FT 3937.1 | I79: Hematologia
E80: ESTADO DO RIO GRANDE D
A81: Baixado | B81: 45903 | C81: 0 | D81: 14138 | E81: 632 Ordem Bancária | F81: 202509020022172 | G81: 2314.31 | H81: FT 3988.1 | I81: Hematologia
E82: ESTADO DO RIO GRANDE D
B83: 45903 | C83: 1533 | D83: 99015 | E83: 470 Transferência enviada | F83: 551845000113366 | G83: 3605.31
E84: 03/09 14:25 JONATAN EDUARDO M SILVA
B85: 45903 | C85: 1533 | D85: 99015 | E85: 470 Transferência enviada | F85: 552035000108588 | G85: 4243
E86: 03/09 14:27 RHOZA MARIA ARAUJO DE ME
B87: 45903 | C87: 0 | D87: 13105 | E87: 109 Pagamento de Boleto | F87: 90301 | G87: 284.65
E88: FARMAUM NATAL M LTDA
B89: 45903 | C89: 0 | D89: 13105 | E89: 109 Pagamento de Boleto | F89: 90302 | G89: 226.14
E90: FARMAUM NATAL M LTDA
B91: 45903 | C91: 0 | D91: 13105 | E91: 109 Pagamento de Boleto | F91: 90303 | G91: 339.81
E92: PROFARMA DISTRIBUIDORA DE PROD
B93: 45903 | C93: 0 | D93: 13105 | E93: 109 Pagamento de Boleto | F93: 90304 | G93: 659.8
E94: BR COMERCIO DE ELETRONICOS LTD
B95: 45903 | C95: 0 | D95: 13105 | E95: 109 Pagamento de Boleto | F95: 90305 | G95: 706.66
E96: APPARAT BRASIL C R I LTDA
B97: 45903 | C97: 0 | D97: 13105 | E97: 109 Pagamento de Boleto | F97: 90306 | G97: 849.45
E98: APPARAT BRASIL C R I LTDA
B99: 45903 | C99: 0 | D99: 13105 | E99: 109 Pagamento de Boleto | F99: 90307 | G99: 4914.67
E100: EBRAM PROD LABORATORIAIS LTDA
...

Sheet Out
J1: Hematologia/165 = | K1: =SUMIF(I:I,"Hematologia", G:G) -> 49957.2 | L1: Total = | M1: =SUBTOTAL(9,Tabelaout[Valor R$]) -> 107252.61
J2: Coagulação/141 = | K2: =SUMIF(I:I,"Coagulação", G:G) -> 12900.83 | L2: Baixados = | M2: =SUMIF(A:A,"Baixado",G:G) -> 105318.02
J3: Ionograma/220 = | K3: =SUMIF(I:I,"Ionograma", G:G) -> 42459.99 | L3: Pendente = | M3: =SUMIF(A:A,"Pendente",G:G) -> 1934.59
A5: Status | B5: Dt. balancete | C5: Ag. origem | D5: Lote | E5: Histórico | F5: Documento | G5: Valor R$ | H5: Fatura | I5: Tipo
B6: 45930 | C6: 0 | D6: 0 | E6: 000 Saldo Anterior | G6: 0
B7: 45931 | C7: 2256 | D7: 99021 | E7: 870 Transferência recebida | F7: 612256000106555 | G7: 554.15
E8: 01/10 15:27 LAB A C DANTAS LTDA
B9: 45931 | C9: 0 | D9: 14175 | E9: 976 TED-Crédito em Conta | F9: 396438844 | G9: 8000
E10: 748 2207 03319496000159 MEDCAL FARMA H
B11: 45931 | C11: 0 | D11: 14397 | E11: 821 Pix - Recebido | F11: 11105506014392 | G11: 800
E12: 01/10 11:05 48899285000170 GROUP PMD
B13: 45931 | C13: 0 | D13: 14397 | E13: 821 Pix - Recebido | F13: 11515508888002 | G13: 4036.15
E14: 01/10 15:15 20897601000156 BIO ANALISE
B15: 45931 | C15: 0 | D15: 14397 | E15: 821 Pix - Recebido | F15: 11604080538762 | G15: 148.5
E16: 01/10 16:04 35256106000135 PROANALISES
B17: 45931 | C17: 0 | D17: 14397 | E17: 821 Pix - Recebido | F17: 11658498892932 | G17: 638.59
E18: 01/10 16:58 22673815000174 SOUZA E CAR
A19: Baixado | B19: 45931 | C19: 0 | D19: 14138 | E19: 632 Ordem Bancária | F19: 202509300020089 | G19: 289.27 | H19: 4007 | I19: Coagulação
E20: ESTADO DO RIO GRANDE D
A21: Baixado | B21: 45931 | C21: 0 | D21: 14138 | E21: 632 Ordem Bancária | F21: 202509300020103 | G21: 926.63 | H21: 4008 | I21: Coagulação
E22: ESTADO DO RIO GRANDE D
A23: Baixado | B23: 45931 | C23: 0 | D23: 14138 | E23: 632 Ordem Bancária | F23: 202509300020116 | G23: 609.28 | H23: 3997 | I23: Coagulação
E24: ESTADO DO RIO GRANDE D
A25: Baixado | B25: 45931 | C25: 0 | D25: 14138 | E25: 632 Ordem Bancária | F25: 202509300020118 | G25: 609.28 | H25: 3996 | I25: Coagulação
E26: ESTADO DO RIO GRANDE D
B27: 45931 | C27: 1533 | D27: 99008 | E27: 234 Compra com Cartão | F27: 540522 | G27: 188.83
E28: 01/10 08:15 POSTO DINIZ - EMAUS
B29: 45931 | C29: 0 | D29: 13105 | E29: 109 Pagamento de Boleto | F29: 100101 | G29: 1632.23
E30: LABOR IMPORT COMERCIAL IMPORTA
B31: 45931 | C31: 0 | D31: 13105 | E31: 109 Pagamento de Boleto | F31: 100102 | G31: 410.53
E32: INFOX
B33: 45931 | C33: 0 | D33: 13105 | E33: 109 Pagamento de Boleto | F33: 100103 | G33: 186.5
E34: INFOX
B35: 45931 | C35: 0 | D35: 13105 | E35: 109 Pagamento de Boleto | F35: 100104 | G35: 816.5
E36: MEDIARTE COMERCIO E SERVICOS D
B37: 45931 | C37: 0 | D37: 13105 | E37: 109 Pagamento de Boleto | F37: 100105 | G37: 96.96
E38: PJBANK PAGAMENTOS S A_1
B39: 45931 | C39: 0 | D39: 13105 | E39: 109 Pagamento de Boleto | F39: 100106 | G39: 224.48
E40: DISTR DE MEDI SANTA CRUZ LTDA
B41: 45931 | C41: 0 | D41: 13105 | E41: 109 Pagamento de Boleto | F41: 100107 | G41: 37.69
E42: DISTR DE MEDI SANTA CRUZ LTDA
B43: 45931 | C43: 0 | D43: 13105 | E43: 109 Pagamento de Boleto | F43: 100108 | G43: 309.76
E44: POLIFARMA DISTRIBUIDORA DE MED
B45: 45931 | C45: 0 | D45: 13105 | E45: 109 Pagamento de Boleto | F45: 100109 | G45: 406.29
E46: POLIFARMA DISTRIBUIDORA DE MED
B47: 45931 | C47: 0 | D47: 13105 | E47: 109 Pagamento de Boleto | F47: 100110 | G47: 379.56
E48: POLIFARMA DISTRIBUIDORA DE MED
B49: 45931 | C49: 0 | D49: 13105 | E49: 109 Pagamento de Boleto | F49: 100111 | G49: 423.34
E50: POLIFARMA DISTRIBUIDORA DE MED
B51: 45931 | C51: 0 | D51: 13105 | E51: 109 Pagamento de Boleto | F51: 100112 | G51: 878.66
E52: STER BOM IND. E COM. LTDA
B53: 45931 | C53: 0 | D53: 13105 | E53: 109 Pagamento de Boleto | F53: 100113 | G53: 204.55
E54: FARMAUM NATAL M LTDA
B55: 45931 | C55: 0 | D55: 13105 | E55: 109 Pagamento de Boleto | F55: 100114 | G55: 269.82
E56: FARMAUM NATAL M LTDA
B57: 45931 | C57: 0 | D57: 13105 | E57: 109 Pagamento de Boleto | F57: 100115 | G57: 238.26
E58: FARMAUM NATAL M LTDA
B59: 45931 | C59: 0 | D59: 13105 | E59: 109 Pagamento de Boleto | F59: 100116 | G59: 271.41
E60: FARMAUM NATAL M LTDA
B61: 45931 | C61: 0 | D61: 13105 | E61: 109 Pagamento de Boleto | F61: 100117 | G61: 252.91
E62: FARMAUM NATAL M LTDA
B63: 45931 | C63: 0 | D63: 13105 | E63: 109 Pagamento de Boleto | F63: 100118 | G63: 203.13
E64: FARMAUM NATAL M LTDA
B65: 45931 | C65: 0 | D65: 13105 | E65: 109 Pagamento de Boleto | F65: 100119 | G65: 242.37
E66: FARMAUM NATAL M LTDA
B67: 45931 | C67: 0 | D67: 13105 | E67: 109 Pagamento de Boleto | F67: 100120 | G67: 1419.35
E68: LABSYNTH PRODUTOS PARA LABORAT
B69: 45931 | C69: 0 | D69: 13105 | E69: 109 Pagamento de Boleto | F69: 100121 | G69: 748.82
E70: TRANSCOURIER LTDA
B71: 45931 | C71: 0 | D71: 13105 | E71: 109 Pagamento de Boleto | F71: 100122 | G71: 392.62
E72: AUVO TECNOLOGIA S.A.
B73: 45931 | C73: 0 | D73: 13105 | E73: 109 Pagamento de Boleto | F73: 100123 | G73: 1020
E74: CONFIANCA FUNDO DE INVEST EM D
B75: 45931 | C75: 0 | D75: 13105 | E75: 109 Pagamento de Boleto | F75: 100124 | G75: 1442.88
E76: BIOS DIAGNOSTICA I C P B L ME
B77: 45931 | C77: 0 | D77: 13105 | E77: 109 Pagamento de Boleto | F77: 100125 | G77: 318.3
E78: RV TECNOLOGIA E SISTEMAS S A
B79: 45931 | C79: 0 | D79: 13105 | E79: 109 Pagamento de Boleto | F79: 100126 | G79: 1959.46
E80: BANCO VOLKSWAGEN S.A.
B81: 45931 | C81: 0 | D81: 13105 | E81: 109 Pagamento de Boleto | F81: 100127 | G81: 763.33
E82: DPC DISTRIBUIDOR ATACADISTA S
B83: 45931 | C83: 0 | D83: 13105 | E83: 363 Pagto conta telefone | F83: 100128 | G83: 64.49
E84: CLARO S.A.
B85: 45931 | C85: 0 | D85: 13105 | E85: 109 Pagamento de Boleto | F85: 100129 | G85: 1774.22
E86: UNIMED NATAL SOCIEDADE COOPERA
B87: 45931 | C87: 0 | D87: 13105 | E87: 109 Pagamento de Boleto | F87: 100130 | G87: 300.66
E88: TRIER COMERCIO DE SOFTWARES LT
B89: 45931 | C89: 0 | D89: 0 | E89: 798 BB Rende Fácil | F89: 9903 | G89: 1266.06
E90: Rende Facil
B91: 45932 | C91: 0 | D91: 14397 | E91: 821 Pix - Recebido | F91: 21404306828551 | G91: 6507.18
E92: 02/10 14:04 00394429018581 BASE AEREA
B93: 45932 | C93: 0 | D93: 14397 | E93: 821 Pix - Recebido | F93: 21532089013522 | G93: 600
E94: 02/10 15:32 28155001000396 CLINICA SAN
B95: 45932 | C95: 0 | D95: 13105 | E95: 109 Pagamento de Boleto | F95: 100201 | G95: 158.59
E96: AIRSUPPLY LOGISTICA T LTDA
B97: 45932 | C97: 0 | D97: 13105 | E97: 363 Pagto conta telefone | F97: 100202 | G97: 132.96
E98: VIVO RN
B99: 45932 | C99: 0 | D99: 13105 | E99: 109 Pagamento de Boleto | F99: 100203 | G99: 77.26
E100: DISTR DE MEDI SANTA CRUZ LTDA
B101: 45932 | C101: 0 | D101: 13105 | E101: 109 Pagamento de Boleto | F101: 100204 | G101: 273.73
...

Sheet Nov
A1: Status | B1: Dt. balancete | C1: Ag. origem | D1: Lote | E1: Histórico | F1: Documento | G1: Valor R$ | H1: Fatura | I1: Tipo | K1: Hematologia/165 = | L1: =SUMIF(J:J,"Hematologia", H:H) -> 0 | M1: Total = | N1: =SUBTOTAL(9,Ago!$G$2:$G$1026) -> 1072735.4
K2: Coagulação/141 = | L2: =SUMIF(J:J,"Coagulação", H:H) -> 0 | M2: Baixados = | N2: =SUMIF(B:B,"Baixado",H:H) -> 0
K3: TT/TTPA = | L3: =SUMIF(J:J,"TT/TTPA", H:H) -> 0 | M3: Pendente = | N3: =SUMIF(B:B,"Pendente",H:H) -> 0
K4: Ionograma/220 = | L4: =SUMIF(J:J,"Ionograma", H:H) -> 0

Sheet Dez
A1: Status | B1: Dt. balancete | C1: Ag. origem | D1: Lote | E1: Histórico | F1: Documento | G1: Valor R$ | H1: Fatura | I1: Tipo | K1: Hematologia/165 = | L1: =SUMIF(J:J,"Hematologia", H:H) -> 0 | M1: Total = | N1: =SUBTOTAL(9,Ago!$G$2:$G$1026) -> 1072735.4
K2: Coagulação/141 = | L2: =SUMIF(J:J,"Coagulação", H:H) -> 0 | M2: Baixados = | N2: =SUMIF(B:B,"Baixado",H:H) -> 0
K3: TT/TTPA = | L3: =SUMIF(J:J,"TT/TTPA", H:H) -> 0 | M3: Pendente = | N3: =SUMIF(B:B,"Pendente",H:H) -> 0
K4: Ionograma/220 = | L4: =SUMIF(J:J,"Ionograma", H:H) -> 0
